Workbook
Name _: #REF!
Name _____________x1: #REF!
Name _____________x2: #REF!
Name ____________x1: #REF!
Name ____________x2: #REF!
Name ___________x1: #REF!
Name ___________x2: #REF!
Name __________x1: #REF!
Name __________x2: #REF!
Name _________x1: #REF!
Name _________x2: #REF!
Name ________x1: #REF!
Name ________x2: #REF!
Name _______x1: #REF!
Name _______x2: #REF!
Name ______x1: #REF!
Name ______x2: #REF!
Name _____x1: #REF!
Name _____x2: #REF!
Name ____1STYR: #REF!
Name ____bnd2: #REF!
Name ____cod1: #REF!
Name ____cod10: #REF!
Name ____cod2: #REF!
Name ____cod3: #REF!
Name ____cod4: #REF!
Name ____cod5: #REF!
Name ____cod6: #REF!
Name ____cod7: #REF!
Name ____cod8: #REF!
Name ____cod9: #REF!
Name ____let1: #REF!
Name ____ord1: #REF!
Name ____ord2: #REF!
Name ____ord3: #REF!
Name ____rrc1: #REF!
Name ____rrc2: #REF!
Name ____sc1: #REF!
Name ____su1: #REF!
Name ____su2: #REF!
Name ____tdp1: #REF!
Name ____TOP2: #REF!
Name ____TOP3: #REF!
Name ____TOP4: #REF!
Name ____TOP5: #REF!
Name ____TOP6: #REF!
Name ____TOP7: #REF!
Name ____ubr1: #REF!
Name ____vat1: #REF!
Name ____x1: #REF!
Name ____x2: #REF!
Name ___10__123Graph_BCHART_4: #REF!
Name ___11__123Graph_BCHART_5: #REF!
Name ___12__123Graph_BCHART_6: #REF!
Name ___13__123Graph_BCHART_7: #REF!
Name ___14__123Graph_CCHART_4: #REF!
Name ___17__123Graph_XCHART_5: #REF!
Name ___18__123Graph_XCHART_6: #REF!
Name ___19__123Graph_XCHART_7: #REF!
Name ___1STYR: #REF!

Sheet Rédaction BAIL
A1: Article | B1: Désignation | C1: Nom Source | D1: Source | E1: Donnée source | F1: Condition | G1: Entrée correspondante - Option 1 | H1: Commentaire | I1: Condition Option 2 | J1: Entrée correspondante - Option 2 | K1: Commentaire
A2: Comparution | B2: Comparution Bailleur | C2: Société Bailleur | D2: ='1. Données historiques'!B4 | E2: SCI FORGEOT PROPERTY | G2: La Société FORGEOT PROPERTY, société civile Immobilière au capital de 310.000 €, dont le siège social est à PARIS (75017), 267 boulevard Pereire, immatriculée au Registre du Commerce et des Sociétés de PARIS sous le numéro unique d'identification 804 088 094, Représentée par son gérant, la Société F&A ASSET MANAGEMENT, SAS dont le siège social est à Paris (75017) - 267, Boulevard Pereire, immatriculée au Registre du Commerce et des Sociétés de Paris sous le numéro B 824 057 087, Elle-même représentée par son Président Monsieur Maxime FORGEOT, dument habilité à l'effet des présentes. Ci-après dénommée : le « Bailleur »
C3: Société Bailleur | D3: ='1. Données historiques'!B4 | E3: SCI FORGEOT RETAIL | G3: La Société FORGEOT RETAIL, société civile Immobilière au capital de 10.000 €, dont le siège social est à PARIS (75017), 267 boulevard Pereire, immatriculée au Registre du Commerce et des Sociétés de PARIS sous le numéro unique d'identification 804 048 445, Représentée par son gérant, la Société F&A ASSET MANAGEMENT, SAS dont le siège social est à Paris (75017) - 267, Boulevard Pereire, immatriculée au Registre du Commerce et des Sociétés de Paris sous le numéro B 824 057 087, Elle-même représentée par son Président Monsieur Maxime FORGEOT, dument habilité à l'effet des présentes. Ci-après dénommée : le « Bailleur »
C4: Société Bailleur | D4: ='1. Données historiques'!B4 | E4: SCI HSR 1 | G4: La Société HIGH STREET RETAIL 1, société civile Immobilière au capital de 10.000 €, dont le siège social est à PARIS (75017), 267 boulevard Pereire, immatriculée au Registre du Commerce et des Sociétés de PARIS sous le numéro unique d'identification 825 190 317, Représentée par son gérant, la Société F&A ASSET MANAGEMENT, SAS dont le siège social est à Paris (75017) - 267, Boulevard Pereire, immatriculée au Registre du Commerce et des Sociétés de Paris sous le numéro B 824 057 087, Elle-même représentée par son Président Monsieur Maxime FORGEOT, dument habilité à l'effet des présentes. Ci-après dénommée : le « Bailleur »
C5: Société Bailleur | D5: ='1. Données historiques'!B4 | E5: SCI HSR 2 | G5: La Société HIGH STREET RETAIL 2, société civile Immobilière au capital de 10.000 €, dont le siège social est à PARIS (75017), 267 boulevard Pereire, immatriculée au Registre du Commerce et des Sociétés de PARIS sous le numéro unique d'identification 830 917 134, Représentée par son gérant, la Société F&A ASSET MANAGEMENT, SAS dont le siège social est à Paris (75017) - 267, Boulevard Pereire, immatriculée au Registre du Commerce et des Sociétés de Paris sous le numéro B 824 057 087, Elle-même représentée par son Président Monsieur Maxime FORGEOT, dument habilité à l'effet des présentes. Ci-après dénommée : le « Bailleur »
C6: Société Bailleur | D6: ='1. Données historiques'!B4 | E6: SARL HSR 3 | G6: La Société HIGH STREET RETAIL 3, société à responsabilité limitée au capital de 1.000 €, dont le siège social est à PARIS (75017), 267 boulevard Pereire, immatriculée au Registre du Commerce et des Sociétés de PARIS sous le numéro unique d'identification 810 334 102, Représentée par son gérant, la Société F&A ASSET MANAGEMENT, SAS dont le siège social est à Paris (75017) - 267, Boulevard Pereire, immatriculée au Registre du Commerce et des Sociétés de Paris sous le numéro B 824 057 087, Elle-même représentée par son Président Monsieur Maxime FORGEOT, dument habilité à l'effet des présentes. Ci-après dénommée : le « Bailleur »
C7: Société Bailleur | D7: ='1. Données historiques'!B4 | E7: SAS HSR 4 | G7: La Société HIGH STREET RETAIL 4, société par actions simplifiée au capital de 72.000 €, dont le siège social est à PARIS (75017), 267 boulevard Pereire, immatriculée au Registre du Commerce et des Sociétés de PARIS sous le numéro unique d'identification 390 174 589, Représentée par son gérant, la Société F&A ASSET MANAGEMENT, SAS dont le siège social est à Paris (75017) - 267, Boulevard Pereire, immatriculée au Registre du Commerce et des Sociétés de Paris sous le numéro B 824 057 087, Elle-même représentée par son Président Monsieur Maxime FORGEOT, dument habilité à l'effet des présentes. Ci-après dénommée : le « Bailleur »
C8: Société Bailleur | D8: ='1. Données historiques'!B4 | E8: SCI HSR 5 | G8: La Société HIGH STREET RETAIL 5, société civile Immobilière au capital de 10.000 €, dont le siège social est à PARIS (75017), 267 boulevard Pereire, immatriculée au Registre du Commerce et des Sociétés de PARIS sous le numéro unique d'identification 850 407 149, Représentée par son gérant, la Société F&A ASSET MANAGEMENT, SAS dont le siège social est à Paris (75017) - 267, Boulevard Pereire, immatriculée au Registre du Commerce et des Sociétés de Paris sous le numéro B 824 057 087, Elle-même représentée par son Président Monsieur Maxime FORGEOT, dument habilité à l'effet des présentes. Ci-après dénommée : le « Bailleur »
C9: Société Bailleur | D9: ='1. Données historiques'!B4 | E9: SCI HSR 6 | G9: La Société HIGH STREET RETAIL 6, société civile Immobilière au capital de 10.000 €, dont le siège social est à PARIS (75017), 267 boulevard Pereire, immatriculée au Registre du Commerce et des Sociétés de PARIS sous le numéro unique d'identification 914 859 434, Représentée par son gérant, la Société F&A ASSET MANAGEMENT, SAS dont le siège social est à Paris (75017) - 267, Boulevard Pereire, immatriculée au Registre du Commerce et des Sociétés de Paris sous le numéro B 824 057 087, Elle-même représentée par son Président Monsieur Maxime FORGEOT, dument habilité à l'effet des présentes. Ci-après dénommée : le « Bailleur »
C10: Société Bailleur | D10: ='1. Données historiques'!B4 | E10: SCI RETAIL RENNES 1 | G10: La Société HRETAIL RENNES 1, société civile Immobilière au capital de 11.098 €, dont le siège social est à PARIS (75017), 267 boulevard Pereire, immatriculée au Registre du Commerce et des Sociétés de PARIS sous le numéro unique d'identification 801 971 508, Représentée par son gérant, la Société F&A ASSET MANAGEMENT, SAS dont le siège social est à Paris (75017) - 267, Boulevard Pereire, immatriculée au Registre du Commerce et des Sociétés de Paris sous le numéro B 824 057 087, Elle-même représentée par son Président Monsieur Maxime FORGEOT, dument habilité à l'effet des présentes. Ci-après dénommée : le « Bailleur »
C11: Société Bailleur | D11: ='1. Données historiques'!B4 | E11: SCI RETAIL RENNES 2 | G11: La Société RETAIL RENNES 2, société civile Immobilière au capital de 39.748 €, dont le siège social est à PARIS (75017), 267 boulevard Pereire, immatriculée au Registre du Commerce et des Sociétés de PARIS sous le numéro unique d'identification 801 932 617, Représentée par son gérant, la Société F&A ASSET MANAGEMENT, SAS dont le siège social est à Paris (75017) - 267, Boulevard Pereire, immatriculée au Registre du Commerce et des Sociétés de Paris sous le numéro B 824 057 087, Elle-même représentée par son Président Monsieur Maxime FORGEOT, dument habilité à l'effet des présentes. Ci-après dénommée : le « Bailleur »
A12: Comparution | B12: Comparution Preneur | C12: Type Preneur Nom Preneur Siret Preneur | D12: =Validation!B24 | E12: =Liste!I19 -> Personne Physique | G12: Monsieur/Madame [Nom Preneur], né le [.] à [.], [profession], demeurant [.], marié avec Madame |PRÉNOMS + NOM de JEUNE FILLE] née le [.] à [.] sous le régime de la séparation de biens suivant contrat de mariage reçu par Me [NOM DU NOTAIRE] à [.] ayant précédé leur union célébrée le [DATE DU MARIAGE] en la Commune de [.]. Si personne marié sous le régime de la communauté : Monsieur [PRENOMS + NOM], né le [.] à [.], [profession], Et Madame |PRÉNOMS + NOM de JEUNE FILLE] née le [.] à [.], [profession], Demeurant ensemble [.], Mariés sous le régime de la communauté légale suivant mariage célébré le [DATE DU MARIAGE] en la Commune de [.]. Si personne pacsée : Monsieur [PRENOMS + NOM], né le [.] à [.], [profession], demeurant [.], pacsé avec Madame |PRÉNOMS + NOM de JEUNE FILLE] née le [.] à [.] sous le régime de la séparation.
C13: Type Preneur Nom Preneur Siret Preneur | D13: =Validation!B24 | E13: SAS | G13: La société [NOM DE LA SOCIETE], Société [TYPE DE SOCIETE] au capital de [CAPITAL SOCIAL], immatriculée au Registre du Commerce et des Sociétés de [LOCALITE RCS] sous le numéro [N° DE SIRET], dont le siège social est à [ADRESSE DE DOMICILIATION], représentée par Madame/Monsieur [PRESIDENT DE LA SOCIETE], dûment habilité aux fins des présentes en vertu [.], ci-après annexé
C14: Type Preneur Nom Preneur Siret Preneur | D14: =Validation!B24 | E14: SARL | G14: La société [NOM DE LA SOCIETE], Société [TYPE DE SOCIETE] au capital de [CAPITAL SOCIAL], immatriculée au Registre du Commerce et des Sociétés de [LOCALITE RCS] sous le numéro [N° DE SIRET], dont le siège social est à [ADRESSE DE DOMICILIATION], représentée par Madame/Monsieur [PRESIDENT DE LA SOCIETE], dûment habilité aux fins des présentes en vertu [.], ci-après annexé
C15: Type Preneur Nom Preneur Siret Preneur | D15: =Validation!B24 | E15: EURL | G15: La société [NOM DE LA SOCIETE], Société [TYPE DE SOCIETE] au capital de [CAPITAL SOCIAL], immatriculée au Registre du Commerce et des Sociétés de [LOCALITE RCS] sous le numéro [N° DE SIRET], dont le siège social est à [ADRESSE DE DOMICILIATION], représentée par Madame/Monsieur [PRESIDENT DE LA SOCIETE], dûment habilité aux fins des présentes en vertu [.], ci-après annexé
C16: Type Preneur Nom Preneur Siret Preneur | D16: =Validation!B24 | E16: Société en formation | G16: PRÉVOIR si le preneur agit pour le compte d’une société en formation : La société XXXX, société [.] au capital de [.], en cours d’immatriculation auprès du Registre du Commerce et des Sociétés de [.], dont le siège social est à [.], représentée par Madame/Monsieur [.], dûment habilité aux fins des présentes en vertu, Ou si personne physique : Si personne marié sous le régime de la séparation : Monsieur [PRENOMS + NOM], né le [.] à [.], [profession], demeurant [.], marié avec Madame |PRÉNOMS + NOM de JEUNE FILLE] née le [.] à [.] sous le régime de la séparation de biens suivant contrat de mariage reçu par Me [NOM DU NOTAIRE] à [.] ayant précédé leur union célébrée le [DATE DU MARIAGE] en la Commune de [.]. Si personne marié sous le régime de la communauté : Monsieur [PRENOMS + NOM], né le [.] à [.], [profession], Et Madame |PRÉNOMS + NOM de JEUNE FILLE] née le [.] à [.], [profession], Demeurant ensemble [.], Mariés sous le régime de la communauté légale suivant mariage célébré le [DATE DU MARIAGE] en la Commune de [.]. Si personne pacsée : Monsieur [PRENOMS + NOM], né le [.] à [.], [profession], demeurant [.], pacsé avec Madame |PRÉNOMS + NOM de JEUNE FILLE] née le [.] à [.] sous le régime de la séparation. [Idem pour tous les associés de la société en cours de formation] Agissant au nom et pour le compte de la société [●], société [●] au capital de [●] euros dont le siège est situé [●], en cours de formation auprès du Registre du Commerce et des Sociétés de [●]. Il est expressément rappelé que le présent acte est passé et réalisé pour le compte de la société XXXXXXXXXX, société en cours de formation conformément à l’article L.210-6 du Code de Commerce et dans le cadre des dispositions de l'article 1843 du Code civil et du 3e paragraphe de l'article 6 du décret n° 78-704 du 3 juillet 1978. Il est rappelé que, conformément aux dispositions des textes précités, l'immatriculation de la société dont s'agit au Registre du commerce et des sociétés emportera reprise à son profit de ladite opération, qui sera alors réputée avoir été effectuée dès l'origine par la société elle-même. Afin de fixer un terme à la période d'incertitude quant à la personne du Preneur définitif, résultant des dispositions ci-dessus rappelées, si l'immatriculation de la société n'intervient pas dans un délai de DEUX MOIS à compter du présent acte, le présent Bail se trouvera conclu de façon définitive par tous les associés de ladite société, et ce, dans les mêmes proportions que celles de leurs droits dans le capital social. À ce titre, il est précisé que les associés fondateurs sont : - XXXXXXX
A17: Article préliminaire | B17: Conditions suspensives et délais | C17: Conditions suspensives 1, 2, 3, 4. | D17: ='3. Hypothèses'!E38:E41 | E17: =Liste!K19 -> Financement | G17: ARTICLE PRELIMINAIRE : BAIL SOUS CONDITION SUSPENSIVE 1. Condition suspensive et délais Le présent Bail est consenti et accepté par le Bailleur et le Preneur sous réserve de la réalisation de la condition suspensive suivante : - Obtention d’un prêt bancaire par le Preneur d’un montant de [X] € ([EN LETTRES] EUROS). Le Preneur devra justifier au Bailleur, au plus tard [X] ([EN LETTRES]) semaines suivant la signature des présentes, du dépôt d’une demande auprès d’au moins 2 (DEUX) établissement bancaires français, sous peine de caducité du présent Bail ; Ci-après la « Condition Suspensive » Chacune des Parties informera par tous moyens écrit l’autre partie de la réalisation de la condition suspensive qui lui incombe. En tout état de cause, la livraison des Locaux Loués au Preneur emportera levée de ladite condition suspensive sans autre formalité, chacune des Parties s’obligeant d’ores et déjà à respecter l’ensemble des clauses et conditions du présent Bail. Dans l'hypothèse où cette condition ne serait pas réalisée dans le délai indiqué ci-dessus, éventuellement prorogé, les obligations contractées par chacune des Parties au titre du présent Bail seront nulles et non avenues et les Parties reprendront, à ce titre, leur pleine et entière liberté sans indemnité de part et d’autre, les sommes versées par le Preneur lors de la signature du Bail lui seront remboursées. 2. Défaillance de la Condition Suspensive A défaut de réalisation de la Condition Suspensive dans le délai susvisé, les obligations contractées par chacune des Parties seront caduques, et les Parties reprendront leur pleine et entière liberté sans indemnité de part et d’autre, le Preneur ayant parfaitement connaissance de ce que le présent bail s’inscrit dans un contexte de libération desdits locaux laquelle n’est ni garantie et ni prévisible et ne pouvant, à ce titre, engager une quelconque action à l’encontre du Bailleur. Le Bailleur s’engageant à restituer au Preneur les sommes versées par le Preneur lors de la signature du Bail. | I17: Si plusieurs conditions suspensives | J17: ARTICLE PRELIMINAIRE : BAIL SOUS CONDITIONS SUSPENSIVES 1. Conditions suspensives et délais Le présent Bail est consenti et accepté par le Bailleur et le Preneur sous réserve de la réalisation des conditions suspensives suivantes : a. Obtention d’un prêt bancaire par le Preneur d’un montant de [X] € ([EN LETTRES] EUROS). Le Preneur devra justifier au Bailleur, au plus tard [X] ([EN LETTRES]) semaines suivant la signature des présentes, du dépôt d’une demande auprès d’au moins 2 (DEUX) établissement bancaires français, sous peine de caducité du présent Bail ; b. Ci-après les « Conditions Suspensives » Chacune des Parties informera par tous moyens écrit l’autre partie de la réalisation de la condition suspensive qui lui incombe. En tout état de cause, la livraison des Locaux Loués au Preneur emportera levée desdites conditions suspensives sans autre formalité, chacune des Parties s’obligeant d’ores et déjà à respecter l’ensemble des clauses et conditions du présent Bail. Dans l'hypothèse où ces conditions ne seraient pas réalisées dans le délai indiqué ci-dessus, éventuellement prorogé, les obligations contractées par chacune des Parties au titre du présent Bail seront nulles et non avenues et les Parties reprendront, à ce titre, leur pleine et entière liberté sans indemnité de part et d’autre, les sommes versées par le Preneur lors de la signature du Bail lui seront remboursées. 2. Défaillance des Conditions Suspensives A défaut de réalisation des Conditions Suspensives dans le délai susvisé, les obligations contractées par chacune des Parties seront caduques, et les Parties reprendront leur pleine et entière liberté sans indemnité de part et d’autre, le Preneur ayant parfaitement connaissance de ce que le présent bail s’inscrit dans un contexte de libération desdits locaux laquelle n’est ni garantie et ni prévisible et ne pouvant, à ce titre, engager une quelconque action à l’encontre du Bailleur. Le Bailleur s’engageant à restituer au Preneur les sommes versées par le Preneur lors de la signature du Bail. | K17: Si plusieurs conditions suspensives, les ajouter en a. b. etc.
C18: Conditions suspensives 1, 2, 3, 4. | D18: ='3. Hypothèses'!E38:E41 | E18: =Liste!K20 -> Autorisations administratives | G18: ARTICLE PRELIMINAIRE : BAIL SOUS CONDITION SUSPENSIVE 1. Condition suspensive et délais Le présent Bail est consenti et accepté par le Bailleur et le Preneur sous réserve de la réalisation de la condition suspensive suivante : - Obtention par le Preneur de l'ensemble des autorisations administratives pour la réalisation des travaux nécessaires à la bonne exploitation de son activité et à la mise en place dans les Locaux Loués de son concept, à savoir une Déclaration Préalable pour les modifications de façade, une demande d’Autorisation d’aménager un établissement recevant du public (ERP) ou toute autre autorisation administrative qui s’avérerait indispensable à l’ouverture et à l’exploitation des Locaux Loués au vu de la localisation spécifique de ces derniers. Le Preneur s’engage à justifier au Bailleur du dépôt de ces autorisations administratives au plus tard 1 (UN) mois après la signature des présentes. Ci-après la « Condition Suspensive » Chacune des Parties informera par tous moyens écrit l’autre partie de la réalisation de la condition suspensive qui lui incombe. En tout état de cause, la livraison des Locaux Loués au Preneur emportera levée de ladite condition suspensive sans autre formalité, chacune des Parties s’obligeant d’ores et déjà à respecter l’ensemble des clauses et conditions du présent Bail. Dans l'hypothèse où cette condition ne serait pas réalisée dans le délai indiqué ci-dessus, éventuellement prorogé, les obligations contractées par chacune des Parties au titre du présent Bail seront nulles et non avenues et les Parties reprendront, à ce titre, leur pleine et entière liberté sans indemnité de part et d’autre, les sommes versées par le Preneur lors de la signature du Bail lui seront remboursées. 2. Défaillance de la Condition Suspensive A défaut de réalisation de la Condition Suspensive dans le délai susvisé, les obligations contractées par chacune des Parties seront caduques, et les Parties reprendront leur pleine et entière liberté sans indemnité de part et d’autre, le Preneur ayant parfaitement connaissance de ce que le présent bail s’inscrit dans un contexte de libération desdits locaux laquelle n’est ni garantie et ni prévisible et ne pouvant, à ce titre, engager une quelconque action à l’encontre du Bailleur. Le Bailleur s’engageant à restituer au Preneur les sommes versées par le Preneur lors de la signature du Bail. | I18: Si plusieurs conditions suspensives | J18: ARTICLE PRELIMINAIRE : BAIL SOUS CONDITIONS SUSPENSIVES 1. Conditions suspensives et délais Le présent Bail est consenti et accepté par le Bailleur et le Preneur sous réserve de la réalisation des conditions suspensives suivantes : a. Obtention par le Preneur de l'ensemble des autorisations administratives pour la réalisation des travaux nécessaires à la bonne exploitation de son activité et à la mise en place dans les Locaux Loués de son concept, à savoir une Déclaration Préalable pour les modifications de façade, une demande d’Autorisation d’aménager un établissement recevant du public (ERP) ou toute autre autorisation administrative qui s’avérerait indispensable à l’ouverture et à l’exploitation des Locaux Loués au vu de la localisation spécifique de ces derniers. Le Preneur s’engage à justifier au Bailleur du dépôt de ces autorisations administratives au plus tard 1 (UN) mois après la signature des présentes. b. Ci-après les « Conditions Suspensives » Chacune des Parties informera par tous moyens écrit l’autre partie de la réalisation de la condition suspensive qui lui incombe. En tout état de cause, la livraison des Locaux Loués au Preneur emportera levée desdites conditions suspensives sans autre formalité, chacune des Parties s’obligeant d’ores et déjà à respecter l’ensemble des clauses et conditions du présent Bail. Dans l'hypothèse où ces conditions ne seraient pas réalisées dans le délai indiqué ci-dessus, éventuellement prorogé, les obligations contractées par chacune des Parties au titre du présent Bail seront nulles et non avenues et les Parties reprendront, à ce titre, leur pleine et entière liberté sans indemnité de part et d’autre, les sommes versées par le Preneur lors de la signature du Bail lui seront remboursées. 2. Défaillance des Conditions Suspensives A défaut de réalisation des Conditions Suspensives dans le délai susvisé, les obligations contractées par chacune des Parties seront caduques, et les Parties reprendront leur pleine et entière liberté sans indemnité de part et d’autre, le Preneur ayant parfaitement connaissance de ce que le présent bail s’inscrit dans un contexte de libération desdits locaux laquelle n’est ni garantie et ni prévisible et ne pouvant, à ce titre, engager une quelconque action à l’encontre du Bailleur. Le Bailleur s’engageant à restituer au Preneur les sommes versées par le Preneur lors de la signature du Bail.
C19: Conditions suspensives 1, 2, 3, 4. | D19: ='3. Hypothèses'!E38:E41 | E19: =Liste!K21 -> Extraction | G19: ARTICLE PRELIMINAIRE : BAIL SOUS CONDITION SUSPENSIVE 1. Condition suspensive et délais Le présent Bail est consenti et accepté par le Bailleur et le Preneur sous réserve de la réalisation de la condition suspensive suivante : - Obtention par le bailleur d’une autorisation de copropriété pour la réalisation de travaux d’installation d’un conduit d’extraction extérieur. Cette condition suspensive devra être levée au plus tard le [X] ; A ce titre, le preneur s’engage à communiquer au bailleur le dossier de travaux d’installation de la gaine d’extraction contenant l’ensemble des éléments nécessaires à la parfaite validation du projet (devis, visuels, rapport bureau d’étude, etc…) lui permettant de solliciter la convocation d’une assemblée générale. Le dossier susvisé devra être communiqué au bailleur au plus tard le [X]. Le Bailleur s’engage a voté favorablement pour l’adoption de ce projet. Ci-après la « Condition Suspensive » Chacune des Parties informera par tous moyens écrit l’autre partie de la réalisation de la condition suspensive qui lui incombe. En tout état de cause, la livraison des Locaux Loués au Preneur emportera levée de ladite condition suspensive sans autre formalité, chacune des Parties s’obligeant d’ores et déjà à respecter l’ensemble des clauses et conditions du présent Bail. Dans l'hypothèse où cette condition ne serait pas réalisée dans le délai indiqué ci-dessus, éventuellement prorogé, les obligations contractées par chacune des Parties au titre du présent Bail seront nulles et non avenues et les Parties reprendront, à ce titre, leur pleine et entière liberté sans indemnité de part et d’autre, les sommes versées par le Preneur lors de la signature du Bail lui seront remboursées. 2. Défaillance de la Condition Suspensive A défaut de réalisation de la Condition Suspensive dans le délai susvisé, les obligations contractées par chacune des Parties seront caduques, et les Parties reprendront leur pleine et entière liberté sans indemnité de part et d’autre, le Preneur ayant parfaitement connaissance de ce que le présent bail s’inscrit dans un contexte de libération desdits locaux laquelle n’est ni garantie et ni prévisible et ne pouvant, à ce titre, engager une quelconque action à l’encontre du Bailleur. Le Bailleur s’engageant à restituer au Preneur les sommes versées par le Preneur lors de la signature du Bail. | I19: Si plusieurs conditions suspensives | J19: ARTICLE PRELIMINAIRE : BAIL SOUS CONDITIONS SUSPENSIVES 1. Conditions suspensives et délais Le présent Bail est consenti et accepté par le Bailleur et le Preneur sous réserve de la réalisation des conditions suspensives suivantes : a. Obtention par le bailleur d’une autorisation de copropriété pour la réalisation de travaux d’installation d’un conduit d’extraction extérieur. Cette condition suspensive devra être levée au plus tard le [X] ; A ce titre, le preneur s’engage à communiquer au bailleur le dossier de travaux d’installation de la gaine d’extraction contenant l’ensemble des éléments nécessaires à la parfaite validation du projet (devis, visuels, rapport bureau d’étude, etc…) lui permettant de solliciter la convocation d’une assemblée générale. Le dossier susvisé devra être communiqué au bailleur au plus tard le [X]. Le Bailleur s’engage a voté favorablement pour l’adoption de ce projet. b. Ci-après les « Conditions Suspensives » Chacune des Parties informera par tous moyens écrit l’autre partie de la réalisation de la condition suspensive qui lui incombe. En tout état de cause, la livraison des Locaux Loués au Preneur emportera levée desdites conditions suspensives sans autre formalité, chacune des Parties s’obligeant d’ores et déjà à respecter l’ensemble des clauses et conditions du présent Bail. Dans l'hypothèse où ces conditions ne seraient pas réalisées dans le délai indiqué ci-dessus, éventuellement prorogé, les obligations contractées par chacune des Parties au titre du présent Bail seront nulles et non avenues et les Parties reprendront, à ce titre, leur pleine et entière liberté sans indemnité de part et d’autre, les sommes versées par le Preneur lors de la signature du Bail lui seront remboursées. 2. Défaillance des Conditions Suspensives A défaut de réalisation des Conditions Suspensives dans le délai susvisé, les obligations contractées par chacune des Parties seront caduques, et les Parties reprendront leur pleine et entière liberté sans indemnité de part et d’autre, le Preneur ayant parfaitement connaissance de ce que le présent bail s’inscrit dans un contexte de libération desdits locaux laquelle n’est ni garantie et ni prévisible et ne pouvant, à ce titre, engager une quelconque action à l’encontre du Bailleur. Le Bailleur s’engageant à restituer au Preneur les sommes versées par le Preneur lors de la signature du Bail.
C20: Conditions suspensives 1, 2, 3, 4. | D20: ='3. Hypothèses'!E38:E41 | E20: =Liste!K22 -> Libération des locaux | G20: ARTICLE PRELIMINAIRE : BAIL SOUS CONDITION SUSPENSIVE 1. Condition suspensive et délais Le présent Bail est consenti et accepté par le Bailleur et le Preneur sous réserve de la réalisation de la condition suspensive suivante : - Libération effective des Locaux Loués par l’actuel occupant, étant précisé que l’occupant a donné congé pour le [X]. Ci-après la « Condition Suspensive » Chacune des Parties informera par tous moyens écrit l’autre partie de la réalisation de la condition suspensive qui lui incombe. En tout état de cause, la livraison des Locaux Loués au Preneur emportera levée de ladite condition suspensive sans autre formalité, chacune des Parties s’obligeant d’ores et déjà à respecter l’ensemble des clauses et conditions du présent Bail. Dans l'hypothèse où cette condition ne serait pas réalisée dans le délai indiqué ci-dessus, éventuellement prorogé, les obligations contractées par chacune des Parties au titre du présent Bail seront nulles et non avenues et les Parties reprendront, à ce titre, leur pleine et entière liberté sans indemnité de part et d’autre, les sommes versées par le Preneur lors de la signature du Bail lui seront remboursées. 2. Défaillance de la Condition Suspensive A défaut de réalisation de la Condition Suspensive dans le délai susvisé, les obligations contractées par chacune des Parties seront caduques, et les Parties reprendront leur pleine et entière liberté sans indemnité de part et d’autre, le Preneur ayant parfaitement connaissance de ce que le présent bail s’inscrit dans un contexte de libération desdits locaux laquelle n’est ni garantie et ni prévisible et ne pouvant, à ce titre, engager une quelconque action à l’encontre du Bailleur. Le Bailleur s’engageant à restituer au Preneur les sommes versées par le Preneur lors de la signature du Bail. | I20: Si plusieurs conditions suspensives | J20: ARTICLE PRELIMINAIRE : BAIL SOUS CONDITIONS SUSPENSIVES 1. Conditions suspensives et délais Le présent Bail est consenti et accepté par le Bailleur et le Preneur sous réserve de la réalisation des conditions suspensives suivantes : a. Libération effective des Locaux Loués par l’actuel occupant, étant précisé que l’occupant a donné congé pour le [X] ; b. Ci-après les « Conditions Suspensives » Chacune des Parties informera par tous moyens écrit l’autre partie de la réalisation de la condition suspensive qui lui incombe. En tout état de cause, la livraison des Locaux Loués au Preneur emportera levée desdites conditions suspensives sans autre formalité, chacune des Parties s’obligeant d’ores et déjà à respecter l’ensemble des clauses et conditions du présent Bail. Dans l'hypothèse où ces conditions ne seraient pas réalisées dans le délai indiqué ci-dessus, éventuellement prorogé, les obligations contractées par chacune des Parties au titre du présent Bail seront nulles et non avenues et les Parties reprendront, à ce titre, leur pleine et entière liberté sans indemnité de part et d’autre, les sommes versées par le Preneur lors de la signature du Bail lui seront remboursées. 2. Défaillance des Conditions Suspensives A défaut de réalisation des Conditions Suspensives dans le délai susvisé, les obligations contractées par chacune des Parties seront caduques, et les Parties reprendront leur pleine et entière liberté sans indemnité de part et d’autre, le Preneur ayant parfaitement connaissance de ce que le présent bail s’inscrit dans un contexte de libération desdits locaux laquelle n’est ni garantie et ni prévisible et ne pouvant, à ce titre, engager une quelconque action à l’encontre du Bailleur. Le Bailleur s’engageant à restituer au Preneur les sommes versées par le Preneur lors de la signature du Bail.
C21: Conditions suspensives 1, 2, 3, 4. | D21: ='3. Hypothèses'!E38:E41 | E21: =Liste!K23 -> Autre | G21: ARTICLE PRELIMINAIRE : BAIL SOUS CONDITION SUSPENSIVE 1. Condition suspensive et délais Le présent Bail est consenti et accepté par le Bailleur et le Preneur sous réserve de la réalisation de la condition suspensive suivante : - Ci-après la « Condition Suspensive » Chacune des Parties informera par tous moyens écrit l’autre partie de la réalisation de la condition suspensive qui lui incombe. En tout état de cause, la livraison des Locaux Loués au Preneur emportera levée de ladite condition suspensive sans autre formalité, chacune des Parties s’obligeant d’ores et déjà à respecter l’ensemble des clauses et conditions du présent Bail. Dans l'hypothèse où cette condition ne serait pas réalisée dans le délai indiqué ci-dessus, éventuellement prorogé, les obligations contractées par chacune des Parties au titre du présent Bail seront nulles et non avenues et les Parties reprendront, à ce titre, leur pleine et entière liberté sans indemnité de part et d’autre, les sommes versées par le Preneur lors de la signature du Bail lui seront remboursées. 2. Défaillance de la Condition Suspensive A défaut de réalisation de la Condition Suspensive dans le délai susvisé, les obligations contractées par chacune des Parties seront caduques, et les Parties reprendront leur pleine et entière liberté sans indemnité de part et d’autre, le Preneur ayant parfaitement connaissance de ce que le présent bail s’inscrit dans un contexte de libération desdits locaux laquelle n’est ni garantie et ni prévisible et ne pouvant, à ce titre, engager une quelconque action à l’encontre du Bailleur. Le Bailleur s’engageant à restituer au Preneur les sommes versées par le Preneur lors de la signature du Bail. | I21: Si plusieurs conditions suspensives | J21: ARTICLE PRELIMINAIRE : BAIL SOUS CONDITIONS SUSPENSIVES 1. Conditions suspensives et délais Le présent Bail est consenti et accepté par le Bailleur et le Preneur sous réserve de la réalisation des conditions suspensives suivantes : a. b. Ci-après les « Conditions Suspensives » Chacune des Parties informera par tous moyens écrit l’autre partie de la réalisation de la condition suspensive qui lui incombe. En tout état de cause, la livraison des Locaux Loués au Preneur emportera levée desdites conditions suspensives sans autre formalité, chacune des Parties s’obligeant d’ores et déjà à respecter l’ensemble des clauses et conditions du présent Bail. Dans l'hypothèse où ces conditions ne seraient pas réalisées dans le délai indiqué ci-dessus, éventuellement prorogé, les obligations contractées par chacune des Parties au titre du présent Bail seront nulles et non avenues et les Parties reprendront, à ce titre, leur pleine et entière liberté sans indemnité de part et d’autre, les sommes versées par le Preneur lors de la signature du Bail lui seront remboursées. 2. Défaillance des Conditions Suspensives A défaut de réalisation des Conditions Suspensives dans le délai susvisé, les obligations contractées par chacune des Parties seront caduques, et les Parties reprendront leur pleine et entière liberté sans indemnité de part et d’autre, le Preneur ayant parfaitement connaissance de ce que le présent bail s’inscrit dans un contexte de libération desdits locaux laquelle n’est ni garantie et ni prévisible et ne pouvant, à ce titre, engager une quelconque action à l’encontre du Bailleur. Le Bailleur s’engageant à restituer au Preneur les sommes versées par le Preneur lors de la signature du Bail.
A22: Article 1 | B22: Désignation | C22: Ville ou arrondissement | D22: ='1. Données historiques'!E4 | G22: Dans un immeuble sis à ([Adresse Locaux Loués] (ci-après l’« Immeuble »), au rez-de-chaussée, un local commercial (ci-après les « Locaux Loués ») d’une surface d’environ [Surface totale] m² correspondant au(x) lot(s) de copropriété n°[.] et constitué de[.] et dont le plan est annexé au Bail.
A23: Article 1 | B23: Désignation | C23: Numéro et rue | D23: ='1. Données historiques'!D4
A24: Article 1 | B24: Désignation | C24: Surface totale | D24: ='1. Données historiques'!G4
A25: Article 2 | B25: Durée | C25: Durée du Bail | D25: ='3. Hypothèses'!E10 | F25: Si [Durée du Bail] = 9 | G25: Le présent Bail est conclu et accepté pour une durée de neuf (9) années entières et consécutives prenant effet le [Date de prise d'effet] pour se terminer le [Date de Prise d'effet + 9 ans]. Conformément à l’article L.145-4 du Code de commerce, le Preneur dispose de la faculté de donner congé à l'expiration de chacune des périodes triennales, au moins six mois à l'avance, par lettre recommandée avec demande d'avis de réception ou par acte extrajudiciaire. Si toutefois le Preneur entendait libérer les Locaux Loués avant l’un des termes contractuellement fixés, à quelque titre que ce soit, il sera tenu envers le Bailleur au jour de son départ, sous réserve de la rémunération d'autres chefs de préjudice, au paiement de l'intégralité des loyers, charges, taxes et impôts et autres accessoires dus au titre du Bail, jusqu’à la 1ère date utile de congé et ce, même si le Bailleur a procédé à la relocation des Locaux Loués. Le Bailleur aura également la faculté de donner congé, s’il entend invoquer le bénéfice des dispositions des articles L. 145-18, L. 145-21 et L. 145-24 du Code de Commerce, afin de construire ou reconstruire l’Immeuble existant, de le surélever ou d’exécuter des travaux prescrits ou autorisés dans le cadre d’une opération de restauration immobilière.
A26: Article 2 | B26: Durée | D26: ='3. Hypothèses'!E7 | E26: Date de prise d'effet | F26: Si "Durée du Bail" = 9
A27: Article 2 | B27: Durée | C27: Durée du Bail | D27: ='3. Hypothèses'!E10 | F27: Si [Durée du Bail] supérieur à 9 | G27: 2.1. – Le présent Bail est conclu et accepté pour une durée de [Durée du Bail] ([Durée du Bail en lettres]) années entières et consécutives prenant effet le [Date de prise d'effet] pour se terminer le [Date de prise d'effet + Durée du Bail]. La date d’effet du Bail correspondant au jour de la livraison des Locaux au Preneur. Le Preneur s’engage et accepte irrévocablement le présent Bail pour une durée ferme de [Durée ferme Bail] ([Durée ferme du Bail en lettres]) années pleines, entières et consécutives, commençant le [Date de prise d'effet] pour se terminer le [Date de prise d'effet + Durée ferme Bail] ; cet engagement constituant pour le Bailleur une condition déterminante du présent Bail, sans laquelle il n’aurait pas contracté. À l’issue de cette période de [Durée ferme Bail]([Durée ferme Bail en lettres]) années, le Preneur recouvrera sa faculté de résiliation triennale pour la [Si Durée ferme Bail = 6 ; "2ème" ; Si Durée ferme Bail = 9 ; "3ème"] période triennale à charge pour le Preneur de délivrer un congé soit par acte extrajudiciaire soit par lettre recommandée avec accusé de réception délivré au Bailleur au moins six (6) mois à l’avance. Si toutefois le Preneur entendait libérer les Locaux Loués avant l’un des termes contractuellement fixés, à quelque titre que ce soit, il sera tenu envers le Bailleur au jour de son départ, sous réserve de la rémunération d'autres chefs de préjudice, au paiement de l'intégralité des loyers, charges, taxes et impôts et autres accessoires dus au titre du Bail, jusqu’à la 1ère date utile de congé. Le Bailleur aura la faculté de donner congé, s’il entend invoquer le bénéfice des dispositions des articles L. 145-18, L. 145-21 et L. 145-24 du Code de Commerce, afin de construire ou reconstruire l’Immeuble existant, de le surélever ou d’exécuter des travaux prescrits ou autorisés dans le cadre d’une opération de restauration immobilière. 2.2. – Il est expressément convenu qu’à l’expiration du présent Bail et en cas de renouvellement éventuel dont, par hypothèse, les conditions statutaires seraient remplies par le Preneur, celui-ci interviendra pour une durée de [Durée du Bail] ([durée du Bail en lettres]) années et ce, par dérogation expresse à l’article L.145—12 du Code de commerce.
A28: Article 2 | B28: Durée | C28: Date de prise d'effet | D28: ='3. Hypothèses'!E7 | F28: Si "Durée du Bail" supérieur à 9
A29: Article 2 | B29: Durée | C29: Durée ferme Bail | D29: ='3. Hypothèses'!E11 | F29: Si "Durée du Bail" supérieur à 9
A30: Article 3 | B30: Destination | C30: Destination | D30: =Validation!B27 | G30: Le Preneur devra utiliser les Locaux Loués à usage exclusif de "[Destination]" et sous l’enseigne "[Enseigne] ".
D31: ='3. Hypothèses'!E45 | E31: Destination
D32: ='3. Hypothèses'!E46 | E32: Restauration sans extraction | F32: Si Restauration sans extraction = "Oui" | G32: "Le Preneur reconnaît être pleinement informé qu’au jour de la signature des présentes, il n’existe pas d’extraction dans les Locaux Loués ni de bac à graisse, par conséquent, il s’interdit dans le cadre des activités visées ci-dessus d’effectuer de la cuisson nécessitant une extraction ou une évacuation particulière des graisses. Si le Preneur souhaite toutefois installer une extraction et/ou un bac à graisse, et ce exclusivement après l’obtention de l’accord du Bailleur, il accepte expressément : - De faire son affaire personnelle de l’obtention de toutes les autorisations administratives nécessaires à l’installation desdits équipements et de prendre en charge tous les frais liés à l’obtention desdites autorisations, - De prendre à sa charge exclusive et sous sa responsabilité et à ses frais exclusifs tous les travaux concernant l’installation de ces équipements. En tout état de cause, si l’installation de ces équipements s’avérait techniquement impossible ou en cas de refus des autorisations nécessaires pour l’installation de ces équipements, les parties reconnaissent que la responsabilité du Bailleur ne pourra être engagée. Par ailleurs, le Bailleur se réserve le droit de demander la suppression sans délai des machines ou moteurs qui seraient installés par le Preneur, si leur fonctionnement venait à motiver des réclamations justifiées par des nuisances des locataires ou voisins. Il fera en sorte que le Bailleur ne puisse être inquiété, ni même recherché au sujet de ses équipements et de son activité."
A33: Article 5.3 | B33: Entretien et réparation | D33: ='3. Hypothèses'!E47 | E33: Option Accession | F33: Si [Option Accession] = "Immédiate" | G33: Les transformations et améliorations, tous travaux d'aménagement, d'embellissement, d'améliorations et d’installations réalisés par le Preneur dans les Locaux Loués deviendront propriété immédiate du Bailleur, sans indemnité de part et d’autre.
D34: ='3. Hypothèses'!E47 | E34: Option Accession | F34: Si [Option Accession] = "Fin du bail" | G34: Les transformations et améliorations, tous travaux d'aménagement, d'embellissement, d'améliorations et d’installations réalisés par le Preneur dans les Locaux Loués deviendront propriété du Bailleur, sans indemnité de part et d’autre, à la fin du présent bail.
D35: ='3. Hypothèses'!E47 | E35: Option Accession | F35: Si [Option Accession] = "Fin de jouissance" | G35: Les transformations et améliorations, tous travaux d'aménagement, d'embellissement, d'améliorations et d’installations réalisés par le Preneur dans les Locaux Loués deviendront propriété du Bailleur, sans indemnité de part et d’autre, en fin de jouissance c’est-à-dire au départ du Preneur.
A36: Article 7.1 | B36: Montant du loyer | D36: ='3. Hypothèses'!E8 | E36: Montant du loyer | G36: 7.1. – Montant du loyer Le loyer annuel est fixé, à compter de la prise d’effet du Bail, à la somme de [Montant du loyer] € HT HC ([Montant du loyer en lettres] EUROS HORS TAXES ET HORS CHARGES).
A37: Article 7.2 | B37: Actualisation et indexation | D37: ='3. Hypothèses'!E48 | E37: Actualisation | F37: Si [Actualisation] = "Oui" | G37: 7.2. – Actualisation et indexation du loyer 7.2.1. Actualisation Le loyer sera actualisé de plein droit et sans aucune formalité ni notification préalable en fonction de la variation de l’Indice national des Loyers Commerciaux (ILC) publié trimestriellement par l’INSEE. Cette actualisation interviendra à la date de prise d’effet du Bail, telle que définie à l’Article 2, en prenant pour référence le dernier indice connu à la date de signature du Bail ([.]) et en lui comparant l’indice publié à la date de prise d’effet du Bail. Le Preneur renonce expressément au bénéfice de discussion et à tous recours envers le Bailleur sur les conséquences résultant de l’actualisation du loyer tel que prévu au présent Article. 7.2.2. Indexation
D38: ='3. Hypothèses'!E48 | E38: Actualisation | F38: Si [Actualisation] ="Non" | G38: 7.2. – Indexation du loyer
A39: Article 7.3 | B39: Paiement des loyers | D39: ='3. Hypothèses'!E49 | E39: Paiement | F39: Si [Paiement] = "Prélèvement" | G39: 7.3.2. – Prélèvements sur compte bancaire Le Preneur autorise irrévocablement le Bailleur ou son mandataire à prélever sur le compte bancaire du Preneur, lors de leurs échéances, toutes les sommes qui lui seraient dues au titre du présent Bail. Le Bailleur prélèvera sur le compte bancaire du Preneur qui l’autorise dès à présent et irrévocablement, lors de leur échéance, les sommes qui lui seraient dues. Le Preneur remet au Bailleur le jour de la signature du Bail un mandat de prélèvement SEPA ou un exemplaire de l’imprimé de demande d’autorisation de prélèvement dûment complété, signé et accompagné d’un relevé d’identité bancaire. Le Preneur prendra toutes dispositions pour que son compte soit suffisamment approvisionné pour satisfaire aux prélèvements. À cet effet, leur montant lui sera notifié par le Bailleur au moins huit jours à l’avance. En cas de changement de domiciliation bancaire, le Preneur s’engage à remettre au Bailleur deux mois avant la plus proche échéance, un nouveau mandat de prélèvement SEPA ou un nouvel imprimé de demande d’autorisation de prélèvement dûment complété et signé.
D40: ='3. Hypothèses'!E49 | E40: Paiement | F40: Si [Paiement] = "Virement" | G40: 7.3.2. – Virements sur compte bancaire Le paiement des loyers en principal et accessoires et plus généralement de toutes sommes dues par le Preneur au Bailleur au titre du présent Bail sera effectué par virement bancaire. Il est toutefois expressément convenu entre les Parties qu’en cas de changement d’exploitant, le Bailleur aura la possibilité d’exiger du nouvel exploitant un paiement par prélèvement bancaire des sommes dues au titre du Bail
A41: Article 7.6 | B41: Droit d'entrée | D41: ='3. Hypothèses'!E9 | E41: Droit d'entrée | F41: Si [Droit d'entrée] non vide | G41: 7.6. – Droit d’entrée Le Preneur verse au Bailleur, à titre de droit d’entrée, le jour de la signature des présentes, en un chèque de banque / virement bancaire, la somme de [Droit d'entrée] € HT ([Droit d'entrée en lettres] EUROS HORS TAXES). Les Parties conviennent d’un commun accord que ce droit d’entrée correspond à une indemnité en contrepartie des avantages de la propriété commerciale, laquelle ne s’entend pas comme un complément de loyer et n’est pas soumise à la TVA. Cette somme sera totalement et définitivement acquise au Bailleur sans qu’il puisse être tenu d’en restituer tout ou partie au Preneur pour quelque cause que ce soit et alors même que le Bail consenti viendrait à prendre fin avant son expiration normale pour quelque motif que ce soit.
A42: Article 8 | B42: Garanties | D42: ='3. Hypothèses'!E42 | E42: Durée DG | F42: Si [Durée DG] non vide | G42: 8.1. – Dépôt de Garantie Pour garantir l’ensemble des obligations lui incombant, le Preneur verse au Bailleur, au jour de la signature des présentes, un dépôt de garantie représentant [Durée du DG] mois de loyer hors charges et hors taxes, soit la somme de [Montant du DG] € ([Montant du DG en lettres]EUROS). Le dépôt de garantie sera conservé par le Bailleur et ne sera pas productif d’intérêts au profit du Preneur. Il est expressément convenu que dans le cas où par l’effet de l’indexation, le loyer tel que stipulé ci-dessus, serait augmenté ou diminué, la somme versée à titre de dépôt de garantie sera également, de plein droit et sans formalité, augmentée ou diminuée dans la même proportion. En tout état de cause, le dépôt de garantie ne pourra être inférieur au [Période DG] du loyer effectivement exigible au cours de l’année précédente. Le Bailleur aura le droit de prélever, en cours de Bail, sans formalité sur ledit dépôt de garantie le montant des loyers échus et non réglés ainsi que toute autre somme exigible à un titre quelconque, auquel cas le Preneur sera tenu de compléter à première demande du Bailleur le dépôt de garantie pour le maintenir toujours égal à un terme de loyer. La compensation étant expressément prévue, le Bailleur exercera, ainsi, sur les sommes nanties à son profit toutes les prérogatives y attachées en conformité avec les articles 2073 et suivants du Code civil. En cas de cession du fonds de commerce ou de cession du droit au Bail dûment autorisé, le montant du dépôt de garantie sera remboursé par le cessionnaire au cédant. En cas de résiliation du présent Bail par suite d’inexécution par le Preneur de ses engagements ou pour une cause quelconque imputable au Preneur, ledit dépôt de garantie restera acquis au Bailleur à titre de premiers dommages et intérêts sans préjudice de tous autres. Cette somme sera rendue au Preneur en fin de location après remise des clefs, paiement de tous les loyers et charges, de même que toute somme dont il pourrait être débiteur envers le Bailleur ou dont celui-ci pourrait être rendu responsable par le fait du Preneur à quelque titre que ce soit. Lors du départ du Preneur, pour quelque cause que ce soit, le dépôt de garantie s'imputera par priorité sur le montant des réparations dues par le Preneur. En cas de transmission de la propriété des Locaux Loués et sur lesquels porte le Bail, notamment en cas de vente ou d'apport à une autre société, le dépôt de garantie sera transféré de plein droit aux nouveaux propriétaires successifs des Locaux Loués qui deviendront seuls débiteurs à l’égard du Preneur, ce que ce dernier reconnait et s’engage à ne réclamer le remboursement qu’auxdits acquéreurs. | H42: [Montant du DG] = [Montant du loyer]/12*[Durée DG] [Période DG] = "quart" si [Durée DG] = 3 ; "tiers" si [Durée DG] = 4 ; "moitier" si [Durée DG] = 6 ;
D43: ='3. Hypothèses'!E43 | E43: Durée GAPD | F43: Si [Durée GAPD] non nul | G43: 8.2. – Garantie à Première Demande Pour garantir l'ensemble des obligations lui incombant au titre des présentes, le Preneur s’engage à remettre au Bailleur, dans un délai de [++] mois de la signature des présentes, soit au plus tard le [+++], une garantie bancaire à première demande émanant d'une banque française de premier ordre ayant son siège social en France conforme au modèle ci-après annexé, couvrant le paiement de l'ensemble des loyers, charges et accessoires, impôts et taxes, indemnités d'occupation ainsi que toutes sommes dues en exécution de l'ensemble des clauses et conditions du présent Bail. Le Bailleur reconnaît avoir reçu ce jour de la part du Preneur un virement bancaire / un chèque de banque d’un montant équivalent à celui de la garantie à première demande. Le Bailleur restituera ce montant au Preneur dans un délai maximum d’1 (UN) mois à compter de la réception de la garantie bancaire en bonne et due forme. Il est convenu néanmoins que si le Preneur ne remettait pas de garantie bancaire dans le délai accordé ci-dessus, le virement réalisé par le Preneur le jour de la signature du Bail sera définitivement conservé par le Bailleur à titre de garantie complémentaire / le chèque de banque remis par le Preneur le jour de la signature du Bail sera présenté à l’encaissement et servira de garantie complémentaire. Les Parties conviennent que le montant encaissé ne produira pas d’intérêt en faveur du Preneur et qu’en aucun cas il ne pourra être assimilé à une indemnité forfaitaire et définitive. Dans le cas d’une mise en jeu totale ou partielle de la garantie bancaire, le Preneur s’oblige à délivrer dans le mois au Bailleur une nouvelle garantie bancaire d’un montant identique à celui de la garantie bancaire mise en jeu. Cette garantie sera limitée à [Durée GAPD] ([Durée GAPD en lettres]) mois de loyer HT soit la somme de [Montant GAPD] € ([Montant GAPD en lettres] EUROS TOUTES TAXES COMPRISES) et pourra être mise en jeu par le Bailleur en une ou plusieurs fois. Le montant de cette garantie sera indexé, chaque année à la date d’anniversaire de la prise d’effet du bail en fonction de l’évolution de l’indice des loyers commerciaux publié par l’INSEE dans les mêmes proportions que le loyer du bail. Chaque paiement effectué par la banque en vertu des présentes obligera le Preneur à reconstituer ladite garantie, de telle sorte que celle-ci soit toujours égale à [Durée GAPD] ([Durée GAPD en lettres]) mois de loyer TTC pendant toute la durée du bail. Cette garantie constitue une garantie à première demande autonome et indépendante et ne pourra en aucun cas être interprétée comme un engagement accessoire ou un cautionnement régi par les articles 2288 et suivants du Code civil. En cas de mise en jeu de la garantie susmentionnée, de même qu'en cas de réajustement conventionnel du loyer en cours de bail, une nouvelle garantie de même montant et de même durée devra être remise au Bailleur, de telle sorte que la garantie ainsi offerte se trouve renouvelée et que le contrat de bail ne puisse être poursuivi sans garantie. La présente garantie bancaire liera les successeurs ayant droit de la banque à quelque titre que ce soit, en ce compris d'un fait d'une fusion, cession ou apport partiel d'actif. En outre, en cas de transmission de la propriété des Locaux Loués et sur lesquels porte le bail, notamment en cas de vente ou d'apport à une autre société, la garantie bénéficiera de plein droit aux nouveaux propriétaires successifs des Locaux Loués. En cas de transmission du fonds de commerce ou du droit au bail par quelque mode que ce soit y compris en application de l’article L.145-16 du code de commerce, le nouveau Preneur devra remettre au Bailleur une nouvelle garantie bancaire à première demande d’un même montant et aux mêmes conditions et ce le jour de la signature de l’acte actant du transfert. En cas de poursuite en tacite prolongation du bail en cours, le Preneur devra remettre au Bailleur une nouvelle garantie dans les mêmes termes et conditions, notamment de durée, au plus tard trois mois précédant le terme contractuel du Bail. À défaut, le Bailleur aura la faculté d’appeler la garantie. Il restituera les sommes perçues de ce chef dès la remise d’une nouvelle garantie. En cas de renouvellement de bail, le Preneur s’oblige, dès la prise d’effet du renouvellement de bail à remettre au Bailleur une nouvelle garantie bancaire correspondant à [Durée GAPD] ([Durée GAPD en lettres] LETTRES) mois de loyer TTC du dernier loyer en cours au jour du renouvellement puis à remettre une nouvelle garantie correspondant à [Durée GAPD] ([Durée GAPD en lettres] LETTRES) mois de loyer TTC une fois le loyer de renouvellement fixé, le tout dans les mêmes conditions visées ci-dessus. En cas d’ouverture de procédure de redressement ou de liquidation judiciaire à l’encontre du Preneur, le Bailleur pourra demander, si bon lui semble et même en cas de poursuite du bail, la compensation avec les sommes dues au titre du passif, ce conformément aux dispositions des articles L 622-7, L 631-14 et L 641-3 du Code de Commerce.
A44: Article 19 | B44: Frais et honoraires | D44: ='3. Hypothèses'!E50 | E44: Honoraires Preneur | F44: Si [Honoraires Preneur] non vide | G44: Les honoraires de commercialisation dus à la société [Broker] seront répartis comme suit : • [Honoraires Preneur] € HT HC à la charge du Preneur, exigibles à la livraison des locaux ; • [Honoraires Bailleur] € HT HC à la charge du Bailleur, exigibles à la livraison des locaux.
D45: ='3. Hypothèses'!E52 | E45: Honoraires Bailleur
D46: ='3. Hypothèses'!E50 | E46: Broker
A47: Article 22.2 | B47: Validité DPE | D47: ='4. Grille ESG'!H91 | E47: DPE | F47: Si [DPE] non nul | G47: Le Preneur reconnait avoir reçu avant ce jour le Diagnostic de Performance Énergétique des Locaux Loués, qui en tant que de besoin est annexé aux présentes. Le Bailleur compte mettre à jour le Diagnostic de Performance Énergétique dans les 36 mois à compter de la Date de Prise d’Effet du Bail. A ce titre, le Preneur s’engage à fournir au Bailleur, sur simple demande, les factures d’énergie et d’eau et laissera libre accès aux Locaux Loués au Bailleur ou à son mandataire pour la réalisation dudit diagnostic, sous réserve d’un préavis de 48h.
A48: Article 26 | B48: Dispositions particulières | D48: =Validation!B23 | E48: Nom Preneur | G48: ARTICLE 26 – DISPOSITIONS PARTICULIERES Les Parties insistent sur le fait que le présent Bail a fait l’objet de discussions entre elles. C’est dans ces conditions que les Parties ont décidé, au moyen du présent article, de conférer à certaines stipulations du Bail et ce, convention expresse entre elles un caractère « intuitu personae » au seul profit de la société [Nom Preneur]. En conséquence, il est expressément convenu entre les Parties que dans l'hypothèse où celle-ci ne serait plus l'exploitant des Locaux Loués, ou en cas de cession de quelque nature que ce soit, les dispositions du Bail reprendront leur plein et entier effet et que le présent Article deviendra nul et non avenu. Cela étant convenu, le Bail est complété et/ou modifié par les stipulations suivantes :
A49: Article 26.1 | B49: Paliers | D49: ='3. Hypothèses'!E8 | E49: Montant du loyer | F49: Si [Loyer année 1] non vide | G49: 26.1. – Montant du Loyer – Paliers Le loyer annuel est fixé, à compter de la Date de Prise d’Effet du Bail, à la somme de [Montant du loyer] € HT HC ([Montant du loyer en lettres] EUROS HORS TAXES ET HORS CHARGES). Cependant, à titre exceptionnel au Preneur, il est convenu : ‒ Pour la première année du Bail, soit la période de douze (12) mois commençant à courir à compter de la Date de Prise d’Effet des présentes, que le loyer annuel sera réduit de [Montant Palier 1] € HT ([Montant Palier 1 en lettres] EUROS HORS TAXES). Autrement dit, pour la première année, le loyer annuel sera de [Loyer année 1] € HT HC ([Loyer année 1 en lettres] EUROS HORS TAXES ET HORS CHARGES). ‒ Pour la deuxième année du Bail, soit la période de douze (12) mois commençant à courir à compter du début de la deuxième année à compter de la Date de Prise d’Effet des présentes, que le loyer annuel indexé (en application de l’article 7.2 du présent Bail) sera réduit de [Montant du Palier 2] € HT ([Montant du Palier 2 en lettres] EUROS HORS TAXES). Autrement dit, pour la deuxième année, le loyer annuel sera de [Montant du loyer] € HT HC ([Montant du loyer en lettres] EUROS HORS TAXES ET HORS CHARGES) + indexation - [Montant du Palier 2] € HT ([Montant du Palier 2 en lettres] EUROS HORS TAXES). ‒ Pour la troisième année du Bail, soit la période de douze (12) mois commençant à courir à compter du début de la troisième année à compter de la Date de Prise d’Effet des présentes, que le loyer annuel indexé (en application de l’article 7.2 du présent Bail) sera réduit de [Montant du Palier 3] € HT ([Montant du Palier 3 en lettres] EUROS HORS TAXES). Autrement dit, pour la deuxième année, le loyer annuel sera de [Montant du loyer] € HT HC ([Montant du loyer en lettres] EUROS HORS TAXES ET HORS CHARGES) + indexation - [Montant du Palier 3] € HT ([Montant du Palier 3 en lettres] EUROS HORS TAXES). En conséquence, le loyer de base annuel, indexé dans les conditions du Bail, sera dû en totalité à compter du [Periode paliers] ème anniversaire de la Date de Prise d’Effet du Bail. Il est convenu entre les Parties comme dispositions essentielles et déterminantes du Bail, que les réductions de Loyer susvisées cesseront de s’appliquer, en cas de résolution du Bail aux torts du Preneur pour un (des) motif(s) survenus durant la période ferme de [Durée ferme] ans prévue à l’article 2, le Loyer défini à l’article 7.1 du Bail, indexé redevenant immédiatement exigible. | H49: Il faut autant de paragraphe de paliers que de case non vide entre le Loyer année 1 et Loyer année 6. [Montant du Palier 1] = [Montant du loyer] - [Loyer année 1] ; [Montant du Palier 2] = [Montant du loyer] - [Loyer année 2] ; Etc.
D50: ='3. Hypothèses'!F16 | E50: Loyer année 1
D51: ='3. Hypothèses'!F17 | E51: Loyer année 2
D52: ='3. Hypothèses'!F18 | E52: Loyer année 3
D53: ='3. Hypothèses'!F19 | E53: Loyer année 4
D54: ='3. Hypothèses'!F20 | E54: Loyer année 5
D55: ='3. Hypothèses'!F21 | E55: Loyer année 6
D56: ='3. Hypothèses'!E11 | E56: Durée ferme Bail
A57: Article 26.2 | B57: Franchise | D57: ='3. Hypothèses'!E23 | E57: Durée Franchise | F57: Si [Durée franchise] non vide | G57: 26.2. – Paiement du loyer – Franchise de loyer Par dérogation à l’article 7.3 du Bail, le Loyer ne sera dû qu’à compter de l’expiration d’un délai de [Durée Franchise] ([Durée Franchise en lettres]) mois suivant la Date de Prise d’Effet du Bail, les autres stipulations de l’article 7.3 du Bail restant inchangées.

Sheet Liste données BAIL
A1: Données Primaire
A2: Nom | B2: Source
A3: Nom Preneur | B3: =Validation!B23
A4: Type Preneur | B4: =Validation!B24
A5: Siret Preneur | B5: =Validation!B25
A6: Société Bailleur | B6: ='1. Données historiques'!B4
A7: Ville ou arrondissement | B7: ='1. Données historiques'!E4
A8: Numéro et rue | B8: ='1. Données historiques'!D4
A9: Date LOI | B9: =Validation!B22
A10: Enseigne | B10: ='3. Hypothèses'!E45
A11: Statut Locaux loués | B11: ='1. Données historiques'!J4
A12: Durée Bail | B12: ='3. Hypothèses'!E10
A13: Durée ferme Bail | B13: ='3. Hypothèses'!E11
... A55: Période DG | B55: Si [Durée DG] = 3 ; "quart" ; Si [Durée DG] = 4 ; "tiers"; Si [Durée DG] = 6 ; "moitier";

Sheet Last Forecast
D1: Nav
L2: Début Trim | N2: =DATE(N5,MONTH(N3)-2,1) -> 44652 | O2: =DATE(O5,3*(O6-1)+1,1) -> 44743 | P2: =O3+1 -> 44835 | Q2: =P3+1 -> 44927 | R2: =Q3+1 -> 45017 | S2: =R3+1 -> 45108 | T2: =S3+1 -> 45200 | U2: =T3+1 -> 45292 | V2: =U3+1 -> 45383 | W2: =V3+1 -> 45474 | ... BD2: =BC3+1 -> 48488
L3: Fin Trim | N3: =O2-1 -> 44742 | O3: =DATE(YEAR(O2),MONTH(O2)+3,1)-1 -> 44834 | P3: =DATE(YEAR(P2),MONTH(P2)+3,1)-1 -> 44926 | Q3: =DATE(YEAR(Q2),MONTH(Q2)+3,1)-1 -> 45016 | R3: =DATE(YEAR(R2),MONTH(R2)+3,1)-1 -> 45107 | S3: =DATE(YEAR(S2),MONTH(S2)+3,1)-1 -> 45199 | T3: =DATE(YEAR(T2),MONTH(T2)+3,1)-1 -> 45291 | U3: =DATE(YEAR(U2),MONTH(U2)+3,1)-1 -> 45382 | V3: =DATE(YEAR(V2),MONTH(V2)+3,1)-1 -> 45473 | ... BD3: =DATE(YEAR(BD2),MONTH(BD2)+3,1)-1 -> 48579
L4: Nb jours | N4: =N3-N2+1 -> 91 | O4: =O3-O2+1 -> 92 | P4: =P3-P2+1 -> 92 | Q4: =Q3-Q2+1 -> 90 | R4: =R3-R2+1 -> 91 | S4: =S3-S2+1 -> 92 | T4: =T3-T2+1 -> 92 | U4: =U3-U2+1 -> 91 | ... BD4: =BD3-BD2+1 -> 92
L5: Année | N5: =IF(O6=1,O5-1,O5) -> 2022 | O5: 2022 | P5: =IF(P6=1,O5+1,O5) -> 2022 | Q5: =IF(Q6=1,P5+1,P5) -> 2023 | R5: =IF(R6=1,Q5+1,Q5) -> 2023 | S5: =IF(S6=1,R5+1,R5) -> 2023 | T5: =IF(T6=1,S5+1,S5) -> 2023 | U5: =IF(U6=1,T5+1,T5) -> 2024 | V5: =IF(V6=1,U5+1,U5) -> 2024 | W5: =IF(W6=1,V5+1,V5) -> 2024 | ... BD5: =IF(BD6=1,BC5+1,BC5) -> 2032
L6: Trimestre | N6: =IF(O6=1,4,O6-1) -> 2 | O6: 3 | P6: =IF(O6=4,1,O6+1) -> 4 | Q6: =IF(P6=4,1,P6+1) -> 1 | R6: =IF(Q6=4,1,Q6+1) -> 2 | S6: =IF(R6=4,1,R6+1) -> 3 | T6: =IF(S6=4,1,S6+1) -> 4 | U6: =IF(T6=4,1,T6+1) -> 1 | V6: =IF(U6=4,1,U6+1) -> 2 | W6: =IF(V6=4,1,V6+1) -> 3 | ... BD6: =IF(BC6=4,1,BC6+1) -> 4
C8: HSR | D8: Conso HSR
C9: =C8 -> HSR
C10: =C9 -> HSR | L10: % Palier | O10: =SUMIFS(O$260:O$10216,$L$260:$L$10216,$L10)/COUNTIFS($L$260:$L$10216,$L10) -> 0.14534884 | P10: =SUMIFS(P$260:P$10216,$L$260:$L$10216,$L10)/COUNTIFS($L$260:$L$10216,$L10) -> 0.14092518 | Q10: =SUMIFS(Q$260:Q$10216,$L$260:$L$10216,$L10)/COUNTIFS($L$260:$L$10216,$L10) -> 0.11162791 | R10: =SUMIFS(R$260:R$10216,$L$260:$L$10216,$L10)/COUNTIFS($L$260:$L$10216,$L10) -> 0.075389727 | S10: =SUMIFS(S$260:S$10216,$L$260:$L$10216,$L10)/COUNTIFS($L$260:$L$10216,$L10) -> 0.062815976 | T10: =SUMIFS(T$260:T$10216,$L$260:$L$10216,$L10)/COUNTIFS($L$260:$L$10216,$L10) -> 0.058139535 | U10: =SUMIFS(U$260:U$10216,$L$260:$L$10216,$L10)/COUNTIFS($L$260:$L$10216,$L10) -> 0.04625607 | V10: =SUMIFS(V$260:V$10216,$L$260:$L$10216,$L10)/COUNTIFS($L$260:$L$10216,$L10) -> 0.027855865 | ... BD10: =SUMIFS(BD$260:BD$10216,$L$260:$L$10216,$L10)/COUNTIFS($L$260:$L$10216,$L10) -> 0
C11: =C10 -> HSR | L11: % Loyer | O11: =SUMIFS(O$260:O$10216,$L$260:$L$10216,$L11)/COUNTIFS($L$260:$L$10216,$L11) -> 0.85452477 | P11: =SUMIFS(P$260:P$10216,$L$260:$L$10216,$L11)/COUNTIFS($L$260:$L$10216,$L11) -> 0.79657482 | Q11: =SUMIFS(Q$260:Q$10216,$L$260:$L$10216,$L11)/COUNTIFS($L$260:$L$10216,$L11) -> 0.78107235 | R11: =SUMIFS(R$260:R$10216,$L$260:$L$10216,$L11)/COUNTIFS($L$260:$L$10216,$L11) -> 0.7751725 | S11: =SUMIFS(S$260:S$10216,$L$260:$L$10216,$L11)/COUNTIFS($L$260:$L$10216,$L11) -> 0.75195905 | T11: =SUMIFS(T$260:T$10216,$L$260:$L$10216,$L11)/COUNTIFS($L$260:$L$10216,$L11) -> 0.74930485 | U11: =SUMIFS(U$260:U$10216,$L$260:$L$10216,$L11)/COUNTIFS($L$260:$L$10216,$L11) -> 0.73786098 | V11: =SUMIFS(V$260:V$10216,$L$260:$L$10216,$L11)/COUNTIFS($L$260:$L$10216,$L11) -> 0.73255814 | ... BD11: =SUMIFS(BD$260:BD$10216,$L$260:$L$10216,$L11)/COUNTIFS($L$260:$L$10216,$L11) -> 0.011627907
C12: =C11 -> HSR | L12: % Vacance loyer futur | O12: =SUMIFS(O$260:O$10216,$L$260:$L$10216,$L12)/COUNTIFS($L$260:$L$10216,$L12) -> 0.039749747 | P12: =SUMIFS(P$260:P$10216,$L$260:$L$10216,$L12)/COUNTIFS($L$260:$L$10216,$L12) -> 0.023319009 | Q12: =SUMIFS(Q$260:Q$10216,$L$260:$L$10216,$L12)/COUNTIFS($L$260:$L$10216,$L12) -> 0.011627907 | R12: =SUMIFS(R$260:R$10216,$L$260:$L$10216,$L12)/COUNTIFS($L$260:$L$10216,$L12) -> 0.011691797 | S12: =SUMIFS(S$260:S$10216,$L$260:$L$10216,$L12)/COUNTIFS($L$260:$L$10216,$L12) -> 0.0058139535 | T12: =SUMIFS(T$260:T$10216,$L$260:$L$10216,$L12)/COUNTIFS($L$260:$L$10216,$L12) -> 0.0058139535 | U12: =SUMIFS(U$260:U$10216,$L$260:$L$10216,$L12)/COUNTIFS($L$260:$L$10216,$L12) -> 0.0058139535 | V12: =SUMIFS(V$260:V$10216,$L$260:$L$10216,$L12)/COUNTIFS($L$260:$L$10216,$L12) -> 0.0058139535 | ... BD12: =SUMIFS(BD$260:BD$10216,$L$260:$L$10216,$L12)/COUNTIFS($L$260:$L$10216,$L12) -> 0
C13: =C12 -> HSR | L13: % Franchise loyer futur | O13: =SUMIFS(O$260:O$10216,$L$260:$L$10216,$L13)/COUNTIFS($L$260:$L$10216,$L13) -> 0.012702224 | P13: =SUMIFS(P$260:P$10216,$L$260:$L$10216,$L13)/COUNTIFS($L$260:$L$10216,$L13) -> 0.02148635 | Q13: =SUMIFS(Q$260:Q$10216,$L$260:$L$10216,$L13)/COUNTIFS($L$260:$L$10216,$L13) -> 0.010594315 | R13: =SUMIFS(R$260:R$10216,$L$260:$L$10216,$L13)/COUNTIFS($L$260:$L$10216,$L13) -> 0.0038972655 | S13: =SUMIFS(S$260:S$10216,$L$260:$L$10216,$L13)/COUNTIFS($L$260:$L$10216,$L13) -> 0.0079625885 | T13: =SUMIFS(T$260:T$10216,$L$260:$L$10216,$L13)/COUNTIFS($L$260:$L$10216,$L13) -> 0 | U13: =SUMIFS(U$260:U$10216,$L$260:$L$10216,$L13)/COUNTIFS($L$260:$L$10216,$L13) -> 0 | V13: =SUMIFS(V$260:V$10216,$L$260:$L$10216,$L13)/COUNTIFS($L$260:$L$10216,$L13) -> 0 | ... BD13: =SUMIFS(BD$260:BD$10216,$L$260:$L$10216,$L13)/COUNTIFS($L$260:$L$10216,$L13) -> 0
C14: =C13 -> HSR | L14: % Loyer futur | O14: =SUMIFS(O$260:O$10216,$L$260:$L$10216,$L14)/COUNTIFS($L$260:$L$10216,$L14) -> 0.10819009 | P14: =SUMIFS(P$260:P$10216,$L$260:$L$10216,$L14)/COUNTIFS($L$260:$L$10216,$L14) -> 0.19186047 | Q14: =SUMIFS(Q$260:Q$10216,$L$260:$L$10216,$L14)/COUNTIFS($L$260:$L$10216,$L14) -> 0.21899225 | R14: =SUMIFS(R$260:R$10216,$L$260:$L$10216,$L14)/COUNTIFS($L$260:$L$10216,$L14) -> 0.22489139 | S14: =SUMIFS(S$260:S$10216,$L$260:$L$10216,$L14)/COUNTIFS($L$260:$L$10216,$L14) -> 0.2539181 | T14: =SUMIFS(T$260:T$10216,$L$260:$L$10216,$L14)/COUNTIFS($L$260:$L$10216,$L14) -> 0.25663549 | U14: =SUMIFS(U$260:U$10216,$L$260:$L$10216,$L14)/COUNTIFS($L$260:$L$10216,$L14) -> 0.26801687 | V14: =SUMIFS(V$260:V$10216,$L$260:$L$10216,$L14)/COUNTIFS($L$260:$L$10216,$L14) -> 0.2733197 | ... BD14: =SUMIFS(BD$260:BD$10216,$L$260:$L$10216,$L14)/COUNTIFS($L$260:$L$10216,$L14) -> 0.98837209
C15: =C14 -> HSR
C16: =C15 -> HSR | L16: Indice loyer | M16: 1 | N16: 1 | O16: =SUMIFS(O$260:O$10216,$L$260:$L$10216,$L16)/COUNTIFS($L$260:$L$10216,$L16) -> 1.0085478 | P16: =SUMIFS(P$260:P$10216,$L$260:$L$10216,$L16)/COUNTIFS($L$260:$L$10216,$L16) -> 1.0119458 | Q16: =SUMIFS(Q$260:Q$10216,$L$260:$L$10216,$L16)/COUNTIFS($L$260:$L$10216,$L16) -> 1.0154645 | R16: =SUMIFS(R$260:R$10216,$L$260:$L$10216,$L16)/COUNTIFS($L$260:$L$10216,$L16) -> 1.0175441 | S16: =SUMIFS(S$260:S$10216,$L$260:$L$10216,$L16)/COUNTIFS($L$260:$L$10216,$L16) -> 1.0208217 | T16: =SUMIFS(T$260:T$10216,$L$260:$L$10216,$L16)/COUNTIFS($L$260:$L$10216,$L16) -> 1.0226163 | U16: =SUMIFS(U$260:U$10216,$L$260:$L$10216,$L16)/COUNTIFS($L$260:$L$10216,$L16) -> 1.0256211 | V16: =SUMIFS(V$260:V$10216,$L$260:$L$10216,$L16)/COUNTIFS($L$260:$L$10216,$L16) -> 1.0277196 | ... BD16: =SUMIFS(BD$260:BD$10216,$L$260:$L$10216,$L16)/COUNTIFS($L$260:$L$10216,$L16) -> 1.1184204
C17: =C16 -> HSR
C18: =C17 -> HSR | L18: Loyer bail | M18: =L18&"-"&C18 -> Loyer bail-HSR | O18: =SUMIFS(O$260:O$10216,$L$260:$L$10216,$L18) -> 3825536.6 | P18: =SUMIFS(P$260:P$10216,$L$260:$L$10216,$L18) -> 3888068.7 | Q18: =SUMIFS(Q$260:Q$10216,$L$260:$L$10216,$L18) -> 3981091.7 | R18: =SUMIFS(R$260:R$10216,$L$260:$L$10216,$L18) -> 4006343.8 | S18: =SUMIFS(S$260:S$10216,$L$260:$L$10216,$L18) -> 4113503.6 | T18: =SUMIFS(T$260:T$10216,$L$260:$L$10216,$L18) -> 4115017.6 | U18: =SUMIFS(U$260:U$10216,$L$260:$L$10216,$L18) -> 4115745.9 | V18: =SUMIFS(V$260:V$10216,$L$260:$L$10216,$L18) -> 4118535.4 | ... BD18: =SUMIFS(BD$260:BD$10216,$L$260:$L$10216,$L18) -> 4437787.7
C19: =C18 -> HSR | L19: Loyer indexé | M19: =L19&"-"&C19 -> Loyer indexé-HSR | O19: =SUMIFS(O$260:O$10216,$L$260:$L$10216,$L19) -> 4036122.3 | P19: =SUMIFS(P$260:P$10216,$L$260:$L$10216,$L19) -> 4100395.7 | Q19: =SUMIFS(Q$260:Q$10216,$L$260:$L$10216,$L19) -> 4200650.4 | R19: =SUMIFS(R$260:R$10216,$L$260:$L$10216,$L19) -> 4233610.1 | S19: =SUMIFS(S$260:S$10216,$L$260:$L$10216,$L19) -> 4302555.8 | T19: =SUMIFS(T$260:T$10216,$L$260:$L$10216,$L19) -> 4282241.1 | U19: =SUMIFS(U$260:U$10216,$L$260:$L$10216,$L19) -> 4298776.8 | V19: =SUMIFS(V$260:V$10216,$L$260:$L$10216,$L19) -> 4309690.9 | ... BD19: =SUMIFS(BD$260:BD$10216,$L$260:$L$10216,$L19) -> 4722122.9
C20: =C19 -> HSR | L20: Impact palier | M20: =L20&"-"&C20 -> Impact palier-HSR | O20: =SUMIFS(O$260:O$10216,$L$260:$L$10216,$L20) -> -148857.38 | P20: =SUMIFS(P$260:P$10216,$L$260:$L$10216,$L20) -> -169837.15 | Q20: =SUMIFS(Q$260:Q$10216,$L$260:$L$10216,$L20) -> -168325.38 | R20: =SUMIFS(R$260:R$10216,$L$260:$L$10216,$L20) -> -132599.47 | S20: =SUMIFS(S$260:S$10216,$L$260:$L$10216,$L20) -> -142001.8 | T20: =SUMIFS(T$260:T$10216,$L$260:$L$10216,$L20) -> -128512.67 | U20: =SUMIFS(U$260:U$10216,$L$260:$L$10216,$L20) -> -116074.6 | V20: =SUMIFS(V$260:V$10216,$L$260:$L$10216,$L20) -> -101655.29 | ... BD20: =SUMIFS(BD$260:BD$10216,$L$260:$L$10216,$L20) -> 0
C21: =C20 -> HSR | L21: Impact vacance future | M21: =L21&"-"&C21 -> Impact vacance future-HSR | O21: =SUMIFS(O$260:O$10216,$L$260:$L$10216,$L21) -> 0 | P21: =SUMIFS(P$260:P$10216,$L$260:$L$10216,$L21) -> 0 | Q21: =SUMIFS(Q$260:Q$10216,$L$260:$L$10216,$L21) -> 0 | R21: =SUMIFS(R$260:R$10216,$L$260:$L$10216,$L21) -> 0 | S21: =SUMIFS(S$260:S$10216,$L$260:$L$10216,$L21) -> 0 | T21: =SUMIFS(T$260:T$10216,$L$260:$L$10216,$L21) -> 0 | U21: =SUMIFS(U$260:U$10216,$L$260:$L$10216,$L21) -> 0 | V21: =SUMIFS(V$260:V$10216,$L$260:$L$10216,$L21) -> 0 | ... BD21: =SUMIFS(BD$260:BD$10216,$L$260:$L$10216,$L21) -> 0
C22: =C21 -> HSR | L22: Impact franchise | M22: =L22&"-"&C22 -> Impact franchise-HSR | O22: =SUMIFS(O$260:O$10216,$L$260:$L$10216,$L22) -> -75458.531 | P22: =SUMIFS(P$260:P$10216,$L$260:$L$10216,$L22) -> -97035.217 | Q22: =SUMIFS(Q$260:Q$10216,$L$260:$L$10216,$L22) -> -37227.778 | R22: =SUMIFS(R$260:R$10216,$L$260:$L$10216,$L22) -> -53655.473 | S22: =SUMIFS(S$260:S$10216,$L$260:$L$10216,$L22) -> -35951.087 | T22: =SUMIFS(T$260:T$10216,$L$260:$L$10216,$L22) -> 0 | U22: =SUMIFS(U$260:U$10216,$L$260:$L$10216,$L22) -> 0 | V22: =SUMIFS(V$260:V$10216,$L$260:$L$10216,$L22) -> 0 | ... BD22: =SUMIFS(BD$260:BD$10216,$L$260:$L$10216,$L22) -> 0
C23: =C22 -> HSR
C24: =C23 -> HSR | L24: Loyer | M24: =L24&"-"&C24 -> Loyer-HSR | O24: =SUMIFS(O$260:O$10216,$L$260:$L$10216,$L24) -> 3811806.4 | P24: =SUMIFS(P$260:P$10216,$L$260:$L$10216,$L24) -> 3833523.3 | Q24: =SUMIFS(Q$260:Q$10216,$L$260:$L$10216,$L24) -> 3995097.2 | R24: =SUMIFS(R$260:R$10216,$L$260:$L$10216,$L24) -> 4047355.1 | S24: =SUMIFS(S$260:S$10216,$L$260:$L$10216,$L24) -> 4124602.9 | T24: =SUMIFS(T$260:T$10216,$L$260:$L$10216,$L24) -> 4153728.4 | U24: =SUMIFS(U$260:U$10216,$L$260:$L$10216,$L24) -> 4182702.2 | V24: =SUMIFS(V$260:V$10216,$L$260:$L$10216,$L24) -> 4208035.6 | ... BD24: =SUMIFS(BD$260:BD$10216,$L$260:$L$10216,$L24) -> 4722122.9
C25: =C24 -> HSR
C26: =C25 -> HSR | L26: DE / DAB | M26: =L26&"-"&C26 -> DE / DAB-HSR | O26: =SUMIFS(O$260:O$10216,$L$260:$L$10216,$L26) -> 300000 | P26: =SUMIFS(P$260:P$10216,$L$260:$L$10216,$L26) -> 0 | Q26: =SUMIFS(Q$260:Q$10216,$L$260:$L$10216,$L26) -> 0 | R26: =SUMIFS(R$260:R$10216,$L$260:$L$10216,$L26) -> 0 | S26: =SUMIFS(S$260:S$10216,$L$260:$L$10216,$L26) -> 0 | T26: =SUMIFS(T$260:T$10216,$L$260:$L$10216,$L26) -> 0 | U26: =SUMIFS(U$260:U$10216,$L$260:$L$10216,$L26) -> 0 | V26: =SUMIFS(V$260:V$10216,$L$260:$L$10216,$L26) -> 0 | ... BD26: =SUMIFS(BD$260:BD$10216,$L$260:$L$10216,$L26) -> 0
C27: =C26 -> HSR | L27: IR | M27: =L27&"-"&C27 -> IR-HSR | O27: =SUMIFS(O$260:O$10216,$L$260:$L$10216,$L27) -> 1000000 | P27: =SUMIFS(P$260:P$10216,$L$260:$L$10216,$L27) -> 2125000 | Q27: =SUMIFS(Q$260:Q$10216,$L$260:$L$10216,$L27) -> 0 | R27: =SUMIFS(R$260:R$10216,$L$260:$L$10216,$L27) -> 1000000 | S27: =SUMIFS(S$260:S$10216,$L$260:$L$10216,$L27) -> 0 | T27: =SUMIFS(T$260:T$10216,$L$260:$L$10216,$L27) -> 0 | U27: =SUMIFS(U$260:U$10216,$L$260:$L$10216,$L27) -> 0 | V27: =SUMIFS(V$260:V$10216,$L$260:$L$10216,$L27) -> 0 | ... BD27: =SUMIFS(BD$260:BD$10216,$L$260:$L$10216,$L27) -> 0
C28: =C27 -> HSR | L28: FOC | M28: =L28&"-"&C28 -> FOC-HSR | O28: =SUMIFS(O$260:O$10216,$L$260:$L$10216,$L28) -> 0 | P28: =SUMIFS(P$260:P$10216,$L$260:$L$10216,$L28) -> 0 | Q28: =SUMIFS(Q$260:Q$10216,$L$260:$L$10216,$L28) -> 0 | R28: =SUMIFS(R$260:R$10216,$L$260:$L$10216,$L28) -> 300000 | S28: =SUMIFS(S$260:S$10216,$L$260:$L$10216,$L28) -> 0 | T28: =SUMIFS(T$260:T$10216,$L$260:$L$10216,$L28) -> 0 | U28: =SUMIFS(U$260:U$10216,$L$260:$L$10216,$L28) -> 0 | V28: =SUMIFS(V$260:V$10216,$L$260:$L$10216,$L28) -> 0 | ... BD28: =SUMIFS(BD$260:BD$10216,$L$260:$L$10216,$L28) -> 0
C29: =C28 -> HSR | L29: Travaux bailleur | M29: =L29&"-"&C29 -> Travaux bailleur-HSR | O29: =SUMIFS(O$260:O$10216,$L$260:$L$10216,$L29) -> 0 | P29: =SUMIFS(P$260:P$10216,$L$260:$L$10216,$L29) -> 0 | Q29: =SUMIFS(Q$260:Q$10216,$L$260:$L$10216,$L29) -> 0 | R29: =SUMIFS(R$260:R$10216,$L$260:$L$10216,$L29) -> 0 | S29: =SUMIFS(S$260:S$10216,$L$260:$L$10216,$L29) -> 0 | T29: =SUMIFS(T$260:T$10216,$L$260:$L$10216,$L29) -> 0 | U29: =SUMIFS(U$260:U$10216,$L$260:$L$10216,$L29) -> 0 | V29: =SUMIFS(V$260:V$10216,$L$260:$L$10216,$L29) -> 0 | ... BD29: =SUMIFS(BD$260:BD$10216,$L$260:$L$10216,$L29) -> 0
C30: =C29 -> HSR | L30: Charges si vacant | M30: =L30&"-"&C30 -> Charges si vacant-HSR | O30: =SUMIFS(O$260:O$10216,$L$260:$L$10216,$L30) -> -18225.16 | P30: =SUMIFS(P$260:P$10216,$L$260:$L$10216,$L30) -> -16582.25 | Q30: =SUMIFS(Q$260:Q$10216,$L$260:$L$10216,$L30) -> -13280.5 | R30: =SUMIFS(R$260:R$10216,$L$260:$L$10216,$L30) -> -13280.5 | S30: =SUMIFS(S$260:S$10216,$L$260:$L$10216,$L30) -> -13280.5 | T30: =SUMIFS(T$260:T$10216,$L$260:$L$10216,$L30) -> -13280.5 | U30: =SUMIFS(U$260:U$10216,$L$260:$L$10216,$L30) -> -13280.5 | V30: =SUMIFS(V$260:V$10216,$L$260:$L$10216,$L30) -> -13280.5 | ... BD30: =SUMIFS(BD$260:BD$10216,$L$260:$L$10216,$L30) -> 0
C31: =C30 -> HSR
C33: SCI FORGEOT RETAIL | D33: =C33 -> SCI FORGEOT RETAIL
C34: =C33 -> SCI FORGEOT RETAIL
C35: =C34 -> SCI FORGEOT RETAIL | L35: % Palier | O35: =SUMIFS(O$260:O$10216,$L$260:$L$10216,$L35,$C$260:$C$10216,$C35)/COUNTIFS($L$260:$L$10216,$L35,$C$260:$C$10216,$C35) -> 0.055555556 | P35: =SUMIFS(P$260:P$10216,$L$260:$L$10216,$L35,$C$260:$C$10216,$C35)/COUNTIFS($L$260:$L$10216,$L35,$C$260:$C$10216,$C35) -> 0.055555556 | Q35: =SUMIFS(Q$260:Q$10216,$L$260:$L$10216,$L35,$C$260:$C$10216,$C35)/COUNTIFS($L$260:$L$10216,$L35,$C$260:$C$10216,$C35) -> 0 | R35: =SUMIFS(R$260:R$10216,$L$260:$L$10216,$L35,$C$260:$C$10216,$C35)/COUNTIFS($L$260:$L$10216,$L35,$C$260:$C$10216,$C35) -> 0 | S35: =SUMIFS(S$260:S$10216,$L$260:$L$10216,$L35,$C$260:$C$10216,$C35)/COUNTIFS($L$260:$L$10216,$L35,$C$260:$C$10216,$C35) -> 0 | T35: =SUMIFS(T$260:T$10216,$L$260:$L$10216,$L35,$C$260:$C$10216,$C35)/COUNTIFS($L$260:$L$10216,$L35,$C$260:$C$10216,$C35) -> 0 | U35: =SUMIFS(U$260:U$10216,$L$260:$L$10216,$L35,$C$260:$C$10216,$C35)/COUNTIFS($L$260:$L$10216,$L35,$C$260:$C$10216,$C35) -> 0 | V35: =SUMIFS(V$260:V$10216,$L$260:$L$10216,$L35,$C$260:$C$10216,$C35)/COUNTIFS($L$260:$L$10216,$L35,$C$260:$C$10216,$C35) -> 0 | ... BD35: =SUMIFS(BD$260:BD$10216,$L$260:$L$10216,$L35,$C$260:$C$10216,$C35)/COUNTIFS($L$260:$L$10216,$L35,$C$260:$C$10216,$C35) -> 0
C36: =C35 -> SCI FORGEOT RETAIL | L36: % Loyer | O36: =SUMIFS(O$260:O$10216,$L$260:$L$10216,$L36,$C$260:$C$10216,$C36)/COUNTIFS($L$260:$L$10216,$L36,$C$260:$C$10216,$C36) -> 0.88888889 | P36: =SUMIFS(P$260:P$10216,$L$260:$L$10216,$L36,$C$260:$C$10216,$C36)/COUNTIFS($L$260:$L$10216,$L36,$C$260:$C$10216,$C36) -> 0.88888889 | Q36: =SUMIFS(Q$260:Q$10216,$L$260:$L$10216,$L36,$C$260:$C$10216,$C36)/COUNTIFS($L$260:$L$10216,$L36,$C$260:$C$10216,$C36) -> 0.79691358 | R36: =SUMIFS(R$260:R$10216,$L$260:$L$10216,$L36,$C$260:$C$10216,$C36)/COUNTIFS($L$260:$L$10216,$L36,$C$260:$C$10216,$C36) -> 0.77777778 | S36: =SUMIFS(S$260:S$10216,$L$260:$L$10216,$L36,$C$260:$C$10216,$C36)/COUNTIFS($L$260:$L$10216,$L36,$C$260:$C$10216,$C36) -> 0.77777778 | T36: =SUMIFS(T$260:T$10216,$L$260:$L$10216,$L36,$C$260:$C$10216,$C36)/COUNTIFS($L$260:$L$10216,$L36,$C$260:$C$10216,$C36) -> 0.77777778 | U36: =SUMIFS(U$260:U$10216,$L$260:$L$10216,$L36,$C$260:$C$10216,$C36)/COUNTIFS($L$260:$L$10216,$L36,$C$260:$C$10216,$C36) -> 0.77777778 | V36: =SUMIFS(V$260:V$10216,$L$260:$L$10216,$L36,$C$260:$C$10216,$C36)/COUNTIFS($L$260:$L$10216,$L36,$C$260:$C$10216,$C36) -> 0.77777778 | ... BD36: =SUMIFS(BD$260:BD$10216,$L$260:$L$10216,$L36,$C$260:$C$10216,$C36)/COUNTIFS($L$260:$L$10216,$L36,$C$260:$C$10216,$C36) -> 0
C37: =C36 -> SCI FORGEOT RETAIL | L37: % Vacance loyer futur | O37: =SUMIFS(O$260:O$10216,$L$260:$L$10216,$L37,$C$260:$C$10216,$C37)/COUNTIFS($L$260:$L$10216,$L37,$C$260:$C$10216,$C37) -> 0.055555556 | P37: =SUMIFS(P$260:P$10216,$L$260:$L$10216,$L37,$C$260:$C$10216,$C37)/COUNTIFS($L$260:$L$10216,$L37,$C$260:$C$10216,$C37) -> 0.055555556 | Q37: =SUMIFS(Q$260:Q$10216,$L$260:$L$10216,$L37,$C$260:$C$10216,$C37)/COUNTIFS($L$260:$L$10216,$L37,$C$260:$C$10216,$C37) -> 0.055555556 | R37: =SUMIFS(R$260:R$10216,$L$260:$L$10216,$L37,$C$260:$C$10216,$C37)/COUNTIFS($L$260:$L$10216,$L37,$C$260:$C$10216,$C37) -> 0.055555556 | S37: =SUMIFS(S$260:S$10216,$L$260:$L$10216,$L37,$C$260:$C$10216,$C37)/COUNTIFS($L$260:$L$10216,$L37,$C$260:$C$10216,$C37) -> 0 | T37: =SUMIFS(T$260:T$10216,$L$260:$L$10216,$L37,$C$260:$C$10216,$C37)/COUNTIFS($L$260:$L$10216,$L37,$C$260:$C$10216,$C37) -> 0 | U37: =SUMIFS(U$260:U$10216,$L$260:$L$10216,$L37,$C$260:$C$10216,$C37)/COUNTIFS($L$260:$L$10216,$L37,$C$260:$C$10216,$C37) -> 0 | V37: =SUMIFS(V$260:V$10216,$L$260:$L$10216,$L37,$C$260:$C$10216,$C37)/COUNTIFS($L$260:$L$10216,$L37,$C$260:$C$10216,$C37) -> 0 | ... BD37: =SUMIFS(BD$260:BD$10216,$L$260:$L$10216,$L37,$C$260:$C$10216,$C37)/COUNTIFS($L$260:$L$10216,$L37,$C$260:$C$10216,$C37) -> 0
C38: =C37 -> SCI FORGEOT RETAIL | L38: % Franchise loyer futur | O38: =SUMIFS(O$260:O$10216,$L$260:$L$10216,$L38,$C$260:$C$10216,$C38)/COUNTIFS($L$260:$L$10216,$L38,$C$260:$C$10216,$C38) -> 0 | P38: =SUMIFS(P$260:P$10216,$L$260:$L$10216,$L38,$C$260:$C$10216,$C38)/COUNTIFS($L$260:$L$10216,$L38,$C$260:$C$10216,$C38) -> 0 | Q38: =SUMIFS(Q$260:Q$10216,$L$260:$L$10216,$L38,$C$260:$C$10216,$C38)/COUNTIFS($L$260:$L$10216,$L38,$C$260:$C$10216,$C38) -> 0 | R38: =SUMIFS(R$260:R$10216,$L$260:$L$10216,$L38,$C$260:$C$10216,$C38)/COUNTIFS($L$260:$L$10216,$L38,$C$260:$C$10216,$C38) -> 0 | S38: =SUMIFS(S$260:S$10216,$L$260:$L$10216,$L38,$C$260:$C$10216,$C38)/COUNTIFS($L$260:$L$10216,$L38,$C$260:$C$10216,$C38) -> 0.038043478 | T38: =SUMIFS(T$260:T$10216,$L$260:$L$10216,$L38,$C$260:$C$10216,$C38)/COUNTIFS($L$260:$L$10216,$L38,$C$260:$C$10216,$C38) -> 0 | U38: =SUMIFS(U$260:U$10216,$L$260:$L$10216,$L38,$C$260:$C$10216,$C38)/COUNTIFS($L$260:$L$10216,$L38,$C$260:$C$10216,$C38) -> 0 | V38: =SUMIFS(V$260:V$10216,$L$260:$L$10216,$L38,$C$260:$C$10216,$C38)/COUNTIFS($L$260:$L$10216,$L38,$C$260:$C$10216,$C38) -> 0 | ... BD38: =SUMIFS(BD$260:BD$10216,$L$260:$L$10216,$L38,$C$260:$C$10216,$C38)/COUNTIFS($L$260:$L$10216,$L38,$C$260:$C$10216,$C38) -> 0
C39: =C38 -> SCI FORGEOT RETAIL | L39: % Loyer futur | O39: =SUMIFS(O$260:O$10216,$L$260:$L$10216,$L39,$C$260:$C$10216,$C39)/COUNTIFS($L$260:$L$10216,$L39,$C$260:$C$10216,$C39) -> 0.055555556 | P39: =SUMIFS(P$260:P$10216,$L$260:$L$10216,$L39,$C$260:$C$10216,$C39)/COUNTIFS($L$260:$L$10216,$L39,$C$260:$C$10216,$C39) -> 0.055555556 | Q39: =SUMIFS(Q$260:Q$10216,$L$260:$L$10216,$L39,$C$260:$C$10216,$C39)/COUNTIFS($L$260:$L$10216,$L39,$C$260:$C$10216,$C39) -> 0.14814815 | R39: =SUMIFS(R$260:R$10216,$L$260:$L$10216,$L39,$C$260:$C$10216,$C39)/COUNTIFS($L$260:$L$10216,$L39,$C$260:$C$10216,$C39) -> 0.16666667 | S39: =SUMIFS(S$260:S$10216,$L$260:$L$10216,$L39,$C$260:$C$10216,$C39)/COUNTIFS($L$260:$L$10216,$L39,$C$260:$C$10216,$C39) -> 0.22222222 | T39: =SUMIFS(T$260:T$10216,$L$260:$L$10216,$L39,$C$260:$C$10216,$C39)/COUNTIFS($L$260:$L$10216,$L39,$C$260:$C$10216,$C39) -> 0.22222222 | U39: =SUMIFS(U$260:U$10216,$L$260:$L$10216,$L39,$C$260:$C$10216,$C39)/COUNTIFS($L$260:$L$10216,$L39,$C$260:$C$10216,$C39) -> 0.22222222 | V39: =SUMIFS(V$260:V$10216,$L$260:$L$10216,$L39,$C$260:$C$10216,$C39)/COUNTIFS($L$260:$L$10216,$L39,$C$260:$C$10216,$C39) -> 0.22222222 | ... BD39: =SUMIFS(BD$260:BD$10216,$L$260:$L$10216,$L39,$C$260:$C$10216,$C39)/COUNTIFS($L$260:$L$10216,$L39,$C$260:$C$10216,$C39) -> 1
C40: =C39 -> SCI FORGEOT RETAIL
C41: =C40 -> SCI FORGEOT RETAIL | L41: Indice loyer | M41: 1 | N41: 1 | O41: =SUMIFS(O$260:O$10216,$L$260:$L$10216,$L41,$C$260:$C$10216,$C41)/COUNTIFS($L$260:$L$10216,$L41,$C$260:$C$10216,$C41) -> 1.0056039 | P41: =SUMIFS(P$260:P$10216,$L$260:$L$10216,$L41,$C$260:$C$10216,$C41)/COUNTIFS($L$260:$L$10216,$L41,$C$260:$C$10216,$C41) -> 1.0104227 | Q41: =SUMIFS(Q$260:Q$10216,$L$260:$L$10216,$L41,$C$260:$C$10216,$C41)/COUNTIFS($L$260:$L$10216,$L41,$C$260:$C$10216,$C41) -> 1.0164198 | R41: =SUMIFS(R$260:R$10216,$L$260:$L$10216,$L41,$C$260:$C$10216,$C41)/COUNTIFS($L$260:$L$10216,$L41,$C$260:$C$10216,$C41) -> 1.0175198 | S41: =SUMIFS(S$260:S$10216,$L$260:$L$10216,$L41,$C$260:$C$10216,$C41)/COUNTIFS($L$260:$L$10216,$L41,$C$260:$C$10216,$C41) -> 1.0195246 | T41: =SUMIFS(T$260:T$10216,$L$260:$L$10216,$L41,$C$260:$C$10216,$C41)/COUNTIFS($L$260:$L$10216,$L41,$C$260:$C$10216,$C41) -> 1.0219822 | U41: =SUMIFS(U$260:U$10216,$L$260:$L$10216,$L41,$C$260:$C$10216,$C41)/COUNTIFS($L$260:$L$10216,$L41,$C$260:$C$10216,$C41) -> 1.0265867 | V41: =SUMIFS(V$260:V$10216,$L$260:$L$10216,$L41,$C$260:$C$10216,$C41)/COUNTIFS($L$260:$L$10216,$L41,$C$260:$C$10216,$C41) -> 1.027695 | ... BD41: =SUMIFS(BD$260:BD$10216,$L$260:$L$10216,$L41,$C$260:$C$10216,$C41)/COUNTIFS($L$260:$L$10216,$L41,$C$260:$C$10216,$C41) -> 1.1177269
C42: =C41 -> SCI FORGEOT RETAIL
C43: =C42 -> SCI FORGEOT RETAIL | L43: Loyer bail | M43: =L43&"-"&C43 -> Loyer bail-SCI FORGEOT RETAIL | O43: =SUMIFS(O$260:O$10216,$L$260:$L$10216,$L43,$C$260:$C$10216,$C43) -> 518304.87 | P43: =SUMIFS(P$260:P$10216,$L$260:$L$10216,$L43,$C$260:$C$10216,$C43) -> 518304.87 | Q43: =SUMIFS(Q$260:Q$10216,$L$260:$L$10216,$L43,$C$260:$C$10216,$C43) -> 530671.13 | R43: =SUMIFS(R$260:R$10216,$L$260:$L$10216,$L43,$C$260:$C$10216,$C43) -> 531291.7 | S43: =SUMIFS(S$260:S$10216,$L$260:$L$10216,$L43,$C$260:$C$10216,$C43) -> 561291.7 | T43: =SUMIFS(T$260:T$10216,$L$260:$L$10216,$L43,$C$260:$C$10216,$C43) -> 561291.7 | U43: =SUMIFS(U$260:U$10216,$L$260:$L$10216,$L43,$C$260:$C$10216,$C43) -> 561291.7 | V43: =SUMIFS(V$260:V$10216,$L$260:$L$10216,$L43,$C$260:$C$10216,$C43) -> 561291.7 | ... BD43: =SUMIFS(BD$260:BD$10216,$L$260:$L$10216,$L43,$C$260:$C$10216,$C43) -> 613052.15
C44: =C43 -> SCI FORGEOT RETAIL | L44: Loyer indexé | M44: =L44&"-"&C44 -> Loyer indexé-SCI FORGEOT RETAIL | O44: =SUMIFS(O$260:O$10216,$L$260:$L$10216,$L44,$C$260:$C$10216,$C44) -> 552084.9 | P44: =SUMIFS(P$260:P$10216,$L$260:$L$10216,$L44,$C$260:$C$10216,$C44) -> 554721.77 | Q44: =SUMIFS(Q$260:Q$10216,$L$260:$L$10216,$L44,$C$260:$C$10216,$C44) -> 562530.93 | R44: =SUMIFS(R$260:R$10216,$L$260:$L$10216,$L44,$C$260:$C$10216,$C44) -> 563404.15 | S44: =SUMIFS(S$260:S$10216,$L$260:$L$10216,$L44,$C$260:$C$10216,$C44) -> 594020.63 | T44: =SUMIFS(T$260:T$10216,$L$260:$L$10216,$L44,$C$260:$C$10216,$C44) -> 595365.44 | U44: =SUMIFS(U$260:U$10216,$L$260:$L$10216,$L44,$C$260:$C$10216,$C44) -> 598726.82 | V44: =SUMIFS(V$260:V$10216,$L$260:$L$10216,$L44,$C$260:$C$10216,$C44) -> 599038.19 | ... BD44: =SUMIFS(BD$260:BD$10216,$L$260:$L$10216,$L44,$C$260:$C$10216,$C44) -> 657889.72
C45: =C44 -> SCI FORGEOT RETAIL | L45: Impact palier | M45: =L45&"-"&C45 -> Impact palier-SCI FORGEOT RETAIL | O45: =SUMIFS(O$260:O$10216,$L$260:$L$10216,$L45,$C$260:$C$10216,$C45) -> -1875 | P45: =SUMIFS(P$260:P$10216,$L$260:$L$10216,$L45,$C$260:$C$10216,$C45) -> -1875 | Q45: =SUMIFS(Q$260:Q$10216,$L$260:$L$10216,$L45,$C$260:$C$10216,$C45) -> 0 | R45: =SUMIFS(R$260:R$10216,$L$260:$L$10216,$L45,$C$260:$C$10216,$C45) -> 0 | S45: =SUMIFS(S$260:S$10216,$L$260:$L$10216,$L45,$C$260:$C$10216,$C45) -> -5000 | T45: =SUMIFS(T$260:T$10216,$L$260:$L$10216,$L45,$C$260:$C$10216,$C45) -> -5000 | U45: =SUMIFS(U$260:U$10216,$L$260:$L$10216,$L45,$C$260:$C$10216,$C45) -> -5000 | V45: =SUMIFS(V$260:V$10216,$L$260:$L$10216,$L45,$C$260:$C$10216,$C45) -> -4972.5275 | ... BD45: =SUMIFS(BD$260:BD$10216,$L$260:$L$10216,$L45,$C$260:$C$10216,$C45) -> 0
C46: =C45 -> SCI FORGEOT RETAIL | L46: Impact vacance future | M46: =L46&"-"&C46 -> Impact vacance future-SCI FORGEOT RETAIL | O46: =SUMIFS(O$260:O$10216,$L$260:$L$10216,$L46,$C$260:$C$10216,$C46) -> 0 | P46: =SUMIFS(P$260:P$10216,$L$260:$L$10216,$L46,$C$260:$C$10216,$C46) -> 0 | Q46: =SUMIFS(Q$260:Q$10216,$L$260:$L$10216,$L46,$C$260:$C$10216,$C46) -> 0 | R46: =SUMIFS(R$260:R$10216,$L$260:$L$10216,$L46,$C$260:$C$10216,$C46) -> 0 | S46: =SUMIFS(S$260:S$10216,$L$260:$L$10216,$L46,$C$260:$C$10216,$C46) -> 0 | T46: =SUMIFS(T$260:T$10216,$L$260:$L$10216,$L46,$C$260:$C$10216,$C46) -> 0 | U46: =SUMIFS(U$260:U$10216,$L$260:$L$10216,$L46,$C$260:$C$10216,$C46) -> 0 | V46: =SUMIFS(V$260:V$10216,$L$260:$L$10216,$L46,$C$260:$C$10216,$C46) -> 0 | ... BD46: =SUMIFS(BD$260:BD$10216,$L$260:$L$10216,$L46,$C$260:$C$10216,$C46) -> 0
C47: =C46 -> SCI FORGEOT RETAIL | L47: Impact franchise future | M47: =L47&"-"&C47 -> Impact franchise future-SCI FORGEOT RETAIL | O47: =SUMIFS(O$260:O$10216,$L$260:$L$10216,$L47,$C$260:$C$10216,$C47) -> 0 | P47: =SUMIFS(P$260:P$10216,$L$260:$L$10216,$L47,$C$260:$C$10216,$C47) -> 0 | Q47: =SUMIFS(Q$260:Q$10216,$L$260:$L$10216,$L47,$C$260:$C$10216,$C47) -> 0 | R47: =SUMIFS(R$260:R$10216,$L$260:$L$10216,$L47,$C$260:$C$10216,$C47) -> 0 | S47: =SUMIFS(S$260:S$10216,$L$260:$L$10216,$L47,$C$260:$C$10216,$C47) -> 0 | T47: =SUMIFS(T$260:T$10216,$L$260:$L$10216,$L47,$C$260:$C$10216,$C47) -> 0 | U47: =SUMIFS(U$260:U$10216,$L$260:$L$10216,$L47,$C$260:$C$10216,$C47) -> 0 | V47: =SUMIFS(V$260:V$10216,$L$260:$L$10216,$L47,$C$260:$C$10216,$C47) -> 0 | ... BD47: =SUMIFS(BD$260:BD$10216,$L$260:$L$10216,$L47,$C$260:$C$10216,$C47) -> 0
C48: =C47 -> SCI FORGEOT RETAIL
C49: =C48 -> SCI FORGEOT RETAIL | L49: Loyer | M49: =L49&"-"&C49 -> Loyer-SCI FORGEOT RETAIL | O49: =SUMIFS(O$260:O$10216,$L$260:$L$10216,$L49,$C$260:$C$10216,$C49) -> 550209.9 | P49: =SUMIFS(P$260:P$10216,$L$260:$L$10216,$L49,$C$260:$C$10216,$C49) -> 552846.77 | Q49: =SUMIFS(Q$260:Q$10216,$L$260:$L$10216,$L49,$C$260:$C$10216,$C49) -> 562530.93 | R49: =SUMIFS(R$260:R$10216,$L$260:$L$10216,$L49,$C$260:$C$10216,$C49) -> 563404.15 | S49: =SUMIFS(S$260:S$10216,$L$260:$L$10216,$L49,$C$260:$C$10216,$C49) -> 571901.07 | T49: =SUMIFS(T$260:T$10216,$L$260:$L$10216,$L49,$C$260:$C$10216,$C49) -> 590365.44 | U49: =SUMIFS(U$260:U$10216,$L$260:$L$10216,$L49,$C$260:$C$10216,$C49) -> 593726.82 | V49: =SUMIFS(V$260:V$10216,$L$260:$L$10216,$L49,$C$260:$C$10216,$C49) -> 594065.66 | ... BD49: =SUMIFS(BD$260:BD$10216,$L$260:$L$10216,$L49,$C$260:$C$10216,$C49) -> 657889.72
C50: =C49 -> SCI FORGEOT RETAIL
C51: =C50 -> SCI FORGEOT RETAIL | L51: DE / DAB | M51: =L51&"-"&C51 -> DE / DAB-SCI FORGEOT RETAIL | O51: =SUMIFS(O$260:O$10216,$L$260:$L$10216,$L51,$C$260:$C$10216,$C51) -> 0 | P51: =SUMIFS(P$260:P$10216,$L$260:$L$10216,$L51,$C$260:$C$10216,$C51) -> 0 | Q51: =SUMIFS(Q$260:Q$10216,$L$260:$L$10216,$L51,$C$260:$C$10216,$C51) -> 0 | R51: =SUMIFS(R$260:R$10216,$L$260:$L$10216,$L51,$C$260:$C$10216,$C51) -> 0 | S51: =SUMIFS(S$260:S$10216,$L$260:$L$10216,$L51,$C$260:$C$10216,$C51) -> 0 | T51: =SUMIFS(T$260:T$10216,$L$260:$L$10216,$L51,$C$260:$C$10216,$C51) -> 0 | U51: =SUMIFS(U$260:U$10216,$L$260:$L$10216,$L51,$C$260:$C$10216,$C51) -> 0 | V51: =SUMIFS(V$260:V$10216,$L$260:$L$10216,$L51,$C$260:$C$10216,$C51) -> 0 | ... BD51: =SUMIFS(BD$260:BD$10216,$L$260:$L$10216,$L51,$C$260:$C$10216,$C51) -> 0
C52: =C51 -> SCI FORGEOT RETAIL | L52: IR | M52: =L52&"-"&C52 -> IR-SCI FORGEOT RETAIL | O52: =SUMIFS(O$260:O$10216,$L$260:$L$10216,$L52,$C$260:$C$10216,$C52) -> 0 | P52: =SUMIFS(P$260:P$10216,$L$260:$L$10216,$L52,$C$260:$C$10216,$C52) -> 0 | Q52: =SUMIFS(Q$260:Q$10216,$L$260:$L$10216,$L52,$C$260:$C$10216,$C52) -> 0 | R52: =SUMIFS(R$260:R$10216,$L$260:$L$10216,$L52,$C$260:$C$10216,$C52) -> 0 | S52: =SUMIFS(S$260:S$10216,$L$260:$L$10216,$L52,$C$260:$C$10216,$C52) -> 0 | T52: =SUMIFS(T$260:T$10216,$L$260:$L$10216,$L52,$C$260:$C$10216,$C52) -> 0 | U52: =SUMIFS(U$260:U$10216,$L$260:$L$10216,$L52,$C$260:$C$10216,$C52) -> 0 | V52: =SUMIFS(V$260:V$10216,$L$260:$L$10216,$L52,$C$260:$C$10216,$C52) -> 0 | ... BD52: =SUMIFS(BD$260:BD$10216,$L$260:$L$10216,$L52,$C$260:$C$10216,$C52) -> 0
C53: =C52 -> SCI FORGEOT RETAIL | L53: FOC | M53: =L53&"-"&C53 -> FOC-SCI FORGEOT RETAIL | O53: =SUMIFS(O$260:O$10216,$L$260:$L$10216,$L53,$C$260:$C$10216,$C53) -> 0 | P53: =SUMIFS(P$260:P$10216,$L$260:$L$10216,$L53,$C$260:$C$10216,$C53) -> 0 | Q53: =SUMIFS(Q$260:Q$10216,$L$260:$L$10216,$L53,$C$260:$C$10216,$C53) -> 0 | R53: =SUMIFS(R$260:R$10216,$L$260:$L$10216,$L53,$C$260:$C$10216,$C53) -> 0 | S53: =SUMIFS(S$260:S$10216,$L$260:$L$10216,$L53,$C$260:$C$10216,$C53) -> 0 | T53: =SUMIFS(T$260:T$10216,$L$260:$L$10216,$L53,$C$260:$C$10216,$C53) -> 0 | U53: =SUMIFS(U$260:U$10216,$L$260:$L$10216,$L53,$C$260:$C$10216,$C53) -> 0 | V53: =SUMIFS(V$260:V$10216,$L$260:$L$10216,$L53,$C$260:$C$10216,$C53) -> 0 | ... BD53: =SUMIFS(BD$260:BD$10216,$L$260:$L$10216,$L53,$C$260:$C$10216,$C53) -> 0
C54: =C53 -> SCI FORGEOT RETAIL | L54: Travaux bailleur | M54: =L54&"-"&C54 -> Travaux bailleur-SCI FORGEOT RETAIL | O54: =SUMIFS(O$260:O$10216,$L$260:$L$10216,$L54,$C$260:$C$10216,$C54) -> 0 | P54: =SUMIFS(P$260:P$10216,$L$260:$L$10216,$L54,$C$260:$C$10216,$C54) -> 0 | Q54: =SUMIFS(Q$260:Q$10216,$L$260:$L$10216,$L54,$C$260:$C$10216,$C54) -> 0 | R54: =SUMIFS(R$260:R$10216,$L$260:$L$10216,$L54,$C$260:$C$10216,$C54) -> 0 | S54: =SUMIFS(S$260:S$10216,$L$260:$L$10216,$L54,$C$260:$C$10216,$C54) -> 0 | T54: =SUMIFS(T$260:T$10216,$L$260:$L$10216,$L54,$C$260:$C$10216,$C54) -> 0 | U54: =SUMIFS(U$260:U$10216,$L$260:$L$10216,$L54,$C$260:$C$10216,$C54) -> 0 | V54: =SUMIFS(V$260:V$10216,$L$260:$L$10216,$L54,$C$260:$C$10216,$C54) -> 0 | ... BD54: =SUMIFS(BD$260:BD$10216,$L$260:$L$10216,$L54,$C$260:$C$10216,$C54) -> 0
C55: =C54 -> SCI FORGEOT RETAIL | L55: Charges si vacant | M55: =L55&"-"&C55 -> Charges si vacant-SCI FORGEOT RETAIL | O55: =SUMIFS(O$260:O$10216,$L$260:$L$10216,$L55,$C$260:$C$10216,$C55) -> 0 | P55: =SUMIFS(P$260:P$10216,$L$260:$L$10216,$L55,$C$260:$C$10216,$C55) -> 0 | Q55: =SUMIFS(Q$260:Q$10216,$L$260:$L$10216,$L55,$C$260:$C$10216,$C55) -> 0 | R55: =SUMIFS(R$260:R$10216,$L$260:$L$10216,$L55,$C$260:$C$10216,$C55) -> 0 | S55: =SUMIFS(S$260:S$10216,$L$260:$L$10216,$L55,$C$260:$C$10216,$C55) -> 0 | T55: =SUMIFS(T$260:T$10216,$L$260:$L$10216,$L55,$C$260:$C$10216,$C55) -> 0 | U55: =SUMIFS(U$260:U$10216,$L$260:$L$10216,$L55,$C$260:$C$10216,$C55) -> 0 | V55: =SUMIFS(V$260:V$10216,$L$260:$L$10216,$L55,$C$260:$C$10216,$C55) -> 0 | ... BD55: =SUMIFS(BD$260:BD$10216,$L$260:$L$10216,$L55,$C$260:$C$10216,$C55) -> 0
C56: =C55 -> SCI FORGEOT RETAIL
C58: SCI FORGEOT PROPERTY | D58: =C58 -> SCI FORGEOT PROPERTY
C59: =C58 -> SCI FORGEOT PROPERTY
C60: =C59 -> SCI FORGEOT PROPERTY | L60: % Palier | O60: =SUMIFS(O$260:O$10216,$L$260:$L$10216,$L60,$C$260:$C$10216,$C60)/COUNTIFS($L$260:$L$10216,$L60,$C$260:$C$10216,$C60) -> 0.2 | P60: =SUMIFS(P$260:P$10216,$L$260:$L$10216,$L60,$C$260:$C$10216,$C60)/COUNTIFS($L$260:$L$10216,$L60,$C$260:$C$10216,$C60) -> 0.2 | Q60: =SUMIFS(Q$260:Q$10216,$L$260:$L$10216,$L60,$C$260:$C$10216,$C60)/COUNTIFS($L$260:$L$10216,$L60,$C$260:$C$10216,$C60) -> 0.2 | R60: =SUMIFS(R$260:R$10216,$L$260:$L$10216,$L60,$C$260:$C$10216,$C60)/COUNTIFS($L$260:$L$10216,$L60,$C$260:$C$10216,$C60) -> 0.2 | S60: =SUMIFS(S$260:S$10216,$L$260:$L$10216,$L60,$C$260:$C$10216,$C60)/COUNTIFS($L$260:$L$10216,$L60,$C$260:$C$10216,$C60) -> 0.2 | T60: =SUMIFS(T$260:T$10216,$L$260:$L$10216,$L60,$C$260:$C$10216,$C60)/COUNTIFS($L$260:$L$10216,$L60,$C$260:$C$10216,$C60) -> 0.2 | U60: =SUMIFS(U$260:U$10216,$L$260:$L$10216,$L60,$C$260:$C$10216,$C60)/COUNTIFS($L$260:$L$10216,$L60,$C$260:$C$10216,$C60) -> 0.2 | V60: =SUMIFS(V$260:V$10216,$L$260:$L$10216,$L60,$C$260:$C$10216,$C60)/COUNTIFS($L$260:$L$10216,$L60,$C$260:$C$10216,$C60) -> 0.19340659 | ... BD60: =SUMIFS(BD$260:BD$10216,$L$260:$L$10216,$L60,$C$260:$C$10216,$C60)/COUNTIFS($L$260:$L$10216,$L60,$C$260:$C$10216,$C60) -> 0
C61: =C60 -> SCI FORGEOT PROPERTY | L61: % Loyer | O61: =SUMIFS(O$260:O$10216,$L$260:$L$10216,$L61,$C$260:$C$10216,$C61)/COUNTIFS($L$260:$L$10216,$L61,$C$260:$C$10216,$C61) -> 1 | P61: =SUMIFS(P$260:P$10216,$L$260:$L$10216,$L61,$C$260:$C$10216,$C61)/COUNTIFS($L$260:$L$10216,$L61,$C$260:$C$10216,$C61) -> 0.2 | Q61: =SUMIFS(Q$260:Q$10216,$L$260:$L$10216,$L61,$C$260:$C$10216,$C61)/COUNTIFS($L$260:$L$10216,$L61,$C$260:$C$10216,$C61) -> 0.2 | R61: =SUMIFS(R$260:R$10216,$L$260:$L$10216,$L61,$C$260:$C$10216,$C61)/COUNTIFS($L$260:$L$10216,$L61,$C$260:$C$10216,$C61) -> 0.2 | S61: =SUMIFS(S$260:S$10216,$L$260:$L$10216,$L61,$C$260:$C$10216,$C61)/COUNTIFS($L$260:$L$10216,$L61,$C$260:$C$10216,$C61) -> 0.2 | T61: =SUMIFS(T$260:T$10216,$L$260:$L$10216,$L61,$C$260:$C$10216,$C61)/COUNTIFS($L$260:$L$10216,$L61,$C$260:$C$10216,$C61) -> 0.2 | U61: =SUMIFS(U$260:U$10216,$L$260:$L$10216,$L61,$C$260:$C$10216,$C61)/COUNTIFS($L$260:$L$10216,$L61,$C$260:$C$10216,$C61) -> 0.2 | V61: =SUMIFS(V$260:V$10216,$L$260:$L$10216,$L61,$C$260:$C$10216,$C61)/COUNTIFS($L$260:$L$10216,$L61,$C$260:$C$10216,$C61) -> 0.2 | ... BD61: =SUMIFS(BD$260:BD$10216,$L$260:$L$10216,$L61,$C$260:$C$10216,$C61)/COUNTIFS($L$260:$L$10216,$L61,$C$260:$C$10216,$C61) -> 0
C62: =C61 -> SCI FORGEOT PROPERTY | L62: % Vacance loyer futur | O62: =SUMIFS(O$260:O$10216,$L$260:$L$10216,$L62,$C$260:$C$10216,$C62)/COUNTIFS($L$260:$L$10216,$L62,$C$260:$C$10216,$C62) -> 0 | P62: =SUMIFS(P$260:P$10216,$L$260:$L$10216,$L62,$C$260:$C$10216,$C62)/COUNTIFS($L$260:$L$10216,$L62,$C$260:$C$10216,$C62) -> 0 | Q62: =SUMIFS(Q$260:Q$10216,$L$260:$L$10216,$L62,$C$260:$C$10216,$C62)/COUNTIFS($L$260:$L$10216,$L62,$C$260:$C$10216,$C62) -> 0 | R62: =SUMIFS(R$260:R$10216,$L$260:$L$10216,$L62,$C$260:$C$10216,$C62)/COUNTIFS($L$260:$L$10216,$L62,$C$260:$C$10216,$C62) -> 0 | S62: =SUMIFS(S$260:S$10216,$L$260:$L$10216,$L62,$C$260:$C$10216,$C62)/COUNTIFS($L$260:$L$10216,$L62,$C$260:$C$10216,$C62) -> 0 | T62: =SUMIFS(T$260:T$10216,$L$260:$L$10216,$L62,$C$260:$C$10216,$C62)/COUNTIFS($L$260:$L$10216,$L62,$C$260:$C$10216,$C62) -> 0 | U62: =SUMIFS(U$260:U$10216,$L$260:$L$10216,$L62,$C$260:$C$10216,$C62)/COUNTIFS($L$260:$L$10216,$L62,$C$260:$C$10216,$C62) -> 0 | V62: =SUMIFS(V$260:V$10216,$L$260:$L$10216,$L62,$C$260:$C$10216,$C62)/COUNTIFS($L$260:$L$10216,$L62,$C$260:$C$10216,$C62) -> 0 | ... BD62: =SUMIFS(BD$260:BD$10216,$L$260:$L$10216,$L62,$C$260:$C$10216,$C62)/COUNTIFS($L$260:$L$10216,$L62,$C$260:$C$10216,$C62) -> 0
C63: =C62 -> SCI FORGEOT PROPERTY | L63: % Franchise loyer futur | O63: =SUMIFS(O$260:O$10216,$L$260:$L$10216,$L63,$C$260:$C$10216,$C63)/COUNTIFS($L$260:$L$10216,$L63,$C$260:$C$10216,$C63) -> 0 | P63: =SUMIFS(P$260:P$10216,$L$260:$L$10216,$L63,$C$260:$C$10216,$C63)/COUNTIFS($L$260:$L$10216,$L63,$C$260:$C$10216,$C63) -> 0 | Q63: =SUMIFS(Q$260:Q$10216,$L$260:$L$10216,$L63,$C$260:$C$10216,$C63)/COUNTIFS($L$260:$L$10216,$L63,$C$260:$C$10216,$C63) -> 0 | R63: =SUMIFS(R$260:R$10216,$L$260:$L$10216,$L63,$C$260:$C$10216,$C63)/COUNTIFS($L$260:$L$10216,$L63,$C$260:$C$10216,$C63) -> 0 | S63: =SUMIFS(S$260:S$10216,$L$260:$L$10216,$L63,$C$260:$C$10216,$C63)/COUNTIFS($L$260:$L$10216,$L63,$C$260:$C$10216,$C63) -> 0 | T63: =SUMIFS(T$260:T$10216,$L$260:$L$10216,$L63,$C$260:$C$10216,$C63)/COUNTIFS($L$260:$L$10216,$L63,$C$260:$C$10216,$C63) -> 0 | U63: =SUMIFS(U$260:U$10216,$L$260:$L$10216,$L63,$C$260:$C$10216,$C63)/COUNTIFS($L$260:$L$10216,$L63,$C$260:$C$10216,$C63) -> 0 | V63: =SUMIFS(V$260:V$10216,$L$260:$L$10216,$L63,$C$260:$C$10216,$C63)/COUNTIFS($L$260:$L$10216,$L63,$C$260:$C$10216,$C63) -> 0 | ... BD63: =SUMIFS(BD$260:BD$10216,$L$260:$L$10216,$L63,$C$260:$C$10216,$C63)/COUNTIFS($L$260:$L$10216,$L63,$C$260:$C$10216,$C63) -> 0
C64: =C63 -> SCI FORGEOT PROPERTY | L64: % Loyer futur | O64: =SUMIFS(O$260:O$10216,$L$260:$L$10216,$L64,$C$260:$C$10216,$C64)/COUNTIFS($L$260:$L$10216,$L64,$C$260:$C$10216,$C64) -> 0.0086956522 | P64: =SUMIFS(P$260:P$10216,$L$260:$L$10216,$L64,$C$260:$C$10216,$C64)/COUNTIFS($L$260:$L$10216,$L64,$C$260:$C$10216,$C64) -> 0.8 | Q64: =SUMIFS(Q$260:Q$10216,$L$260:$L$10216,$L64,$C$260:$C$10216,$C64)/COUNTIFS($L$260:$L$10216,$L64,$C$260:$C$10216,$C64) -> 0.8 | R64: =SUMIFS(R$260:R$10216,$L$260:$L$10216,$L64,$C$260:$C$10216,$C64)/COUNTIFS($L$260:$L$10216,$L64,$C$260:$C$10216,$C64) -> 0.8 | S64: =SUMIFS(S$260:S$10216,$L$260:$L$10216,$L64,$C$260:$C$10216,$C64)/COUNTIFS($L$260:$L$10216,$L64,$C$260:$C$10216,$C64) -> 0.8 | T64: =SUMIFS(T$260:T$10216,$L$260:$L$10216,$L64,$C$260:$C$10216,$C64)/COUNTIFS($L$260:$L$10216,$L64,$C$260:$C$10216,$C64) -> 0.8 | U64: =SUMIFS(U$260:U$10216,$L$260:$L$10216,$L64,$C$260:$C$10216,$C64)/COUNTIFS($L$260:$L$10216,$L64,$C$260:$C$10216,$C64) -> 0.8 | V64: =SUMIFS(V$260:V$10216,$L$260:$L$10216,$L64,$C$260:$C$10216,$C64)/COUNTIFS($L$260:$L$10216,$L64,$C$260:$C$10216,$C64) -> 0.8 | ... BD64: =SUMIFS(BD$260:BD$10216,$L$260:$L$10216,$L64,$C$260:$C$10216,$C64)/COUNTIFS($L$260:$L$10216,$L64,$C$260:$C$10216,$C64) -> 1
C65: =C64 -> SCI FORGEOT PROPERTY
C66: =C65 -> SCI FORGEOT PROPERTY | L66: Indice loyer | M66: 1 | N66: 1 | O66: =SUMIFS(O$260:O$10216,$L$260:$L$10216,$L66,$C$260:$C$10216,$C66)/COUNTIFS($L$260:$L$10216,$L66,$C$260:$C$10216,$C66) -> 1.0096087 | P66: =SUMIFS(P$260:P$10216,$L$260:$L$10216,$L66,$C$260:$C$10216,$C66)/COUNTIFS($L$260:$L$10216,$L66,$C$260:$C$10216,$C66) -> 1.016 | Q66: =SUMIFS(Q$260:Q$10216,$L$260:$L$10216,$L66,$C$260:$C$10216,$C66)/COUNTIFS($L$260:$L$10216,$L66,$C$260:$C$10216,$C66) -> 1.016 | R66: =SUMIFS(R$260:R$10216,$L$260:$L$10216,$L66,$C$260:$C$10216,$C66)/COUNTIFS($L$260:$L$10216,$L66,$C$260:$C$10216,$C66) -> 1.0160673 | S66: =SUMIFS(S$260:S$10216,$L$260:$L$10216,$L66,$C$260:$C$10216,$C66)/COUNTIFS($L$260:$L$10216,$L66,$C$260:$C$10216,$C66) -> 1.0222265 | T66: =SUMIFS(T$260:T$10216,$L$260:$L$10216,$L66,$C$260:$C$10216,$C66)/COUNTIFS($L$260:$L$10216,$L66,$C$260:$C$10216,$C66) -> 1.02616 | U66: =SUMIFS(U$260:U$10216,$L$260:$L$10216,$L66,$C$260:$C$10216,$C66)/COUNTIFS($L$260:$L$10216,$L66,$C$260:$C$10216,$C66) -> 1.02616 | V66: =SUMIFS(V$260:V$10216,$L$260:$L$10216,$L66,$C$260:$C$10216,$C66)/COUNTIFS($L$260:$L$10216,$L66,$C$260:$C$10216,$C66) -> 1.0262279 | ... BD66: =SUMIFS(BD$260:BD$10216,$L$260:$L$10216,$L66,$C$260:$C$10216,$C66)/COUNTIFS($L$260:$L$10216,$L66,$C$260:$C$10216,$C66) -> 1.1222961
C67: =C66 -> SCI FORGEOT PROPERTY
C68: =C67 -> SCI FORGEOT PROPERTY | L68: Loyer bail | M68: =L68&"-"&C68 -> Loyer bail-SCI FORGEOT PROPERTY | O68: =SUMIFS(O$260:O$10216,$L$260:$L$10216,$L68,$C$260:$C$10216,$C68) -> 65150.5 | P68: =SUMIFS(P$260:P$10216,$L$260:$L$10216,$L68,$C$260:$C$10216,$C68) -> 11125 | Q68: =SUMIFS(Q$260:Q$10216,$L$260:$L$10216,$L68,$C$260:$C$10216,$C68) -> 11125 | R68: =SUMIFS(R$260:R$10216,$L$260:$L$10216,$L68,$C$260:$C$10216,$C68) -> 11125 | S68: =SUMIFS(S$260:S$10216,$L$260:$L$10216,$L68,$C$260:$C$10216,$C68) -> 11125 | T68: =SUMIFS(T$260:T$10216,$L$260:$L$10216,$L68,$C$260:$C$10216,$C68) -> 11125 | U68: =SUMIFS(U$260:U$10216,$L$260:$L$10216,$L68,$C$260:$C$10216,$C68) -> 11125 | V68: =SUMIFS(V$260:V$10216,$L$260:$L$10216,$L68,$C$260:$C$10216,$C68) -> 11125 | ... BD68: =SUMIFS(BD$260:BD$10216,$L$260:$L$10216,$L68,$C$260:$C$10216,$C68) -> 13814.507
C69: =C68 -> SCI FORGEOT PROPERTY | L69: Loyer indexé | M69: =L69&"-"&C69 -> Loyer indexé-SCI FORGEOT PROPERTY | O69: =SUMIFS(O$260:O$10216,$L$260:$L$10216,$L69,$C$260:$C$10216,$C69) -> 69081.097 | P69: =SUMIFS(P$260:P$10216,$L$260:$L$10216,$L69,$C$260:$C$10216,$C69) -> 12101.166 | Q69: =SUMIFS(Q$260:Q$10216,$L$260:$L$10216,$L69,$C$260:$C$10216,$C69) -> 12101.166 | R69: =SUMIFS(R$260:R$10216,$L$260:$L$10216,$L69,$C$260:$C$10216,$C69) -> 12101.166 | S69: =SUMIFS(S$260:S$10216,$L$260:$L$10216,$L69,$C$260:$C$10216,$C69) -> 12189.294 | T69: =SUMIFS(T$260:T$10216,$L$260:$L$10216,$L69,$C$260:$C$10216,$C69) -> 12222.178 | U69: =SUMIFS(U$260:U$10216,$L$260:$L$10216,$L69,$C$260:$C$10216,$C69) -> 12222.178 | V69: =SUMIFS(V$260:V$10216,$L$260:$L$10216,$L69,$C$260:$C$10216,$C69) -> 12222.178 | ... BD69: =SUMIFS(BD$260:BD$10216,$L$260:$L$10216,$L69,$C$260:$C$10216,$C69) -> 14703.938
C70: =C69 -> SCI FORGEOT PROPERTY | L70: Impact palier | M70: =L70&"-"&C70 -> Impact palier-SCI FORGEOT PROPERTY | O70: =SUMIFS(O$260:O$10216,$L$260:$L$10216,$L70,$C$260:$C$10216,$C70) -> -4414.782 | P70: =SUMIFS(P$260:P$10216,$L$260:$L$10216,$L70,$C$260:$C$10216,$C70) -> -4414.782 | Q70: =SUMIFS(Q$260:Q$10216,$L$260:$L$10216,$L70,$C$260:$C$10216,$C70) -> -4414.782 | R70: =SUMIFS(R$260:R$10216,$L$260:$L$10216,$L70,$C$260:$C$10216,$C70) -> -4373.5732 | S70: =SUMIFS(S$260:S$10216,$L$260:$L$10216,$L70,$C$260:$C$10216,$C70) -> -3164.782 | T70: =SUMIFS(T$260:T$10216,$L$260:$L$10216,$L70,$C$260:$C$10216,$C70) -> -3164.782 | U70: =SUMIFS(U$260:U$10216,$L$260:$L$10216,$L70,$C$260:$C$10216,$C70) -> -3164.782 | V70: =SUMIFS(V$260:V$10216,$L$260:$L$10216,$L70,$C$260:$C$10216,$C70) -> -3060.4485 | ... BD70: =SUMIFS(BD$260:BD$10216,$L$260:$L$10216,$L70,$C$260:$C$10216,$C70) -> 0
C71: =C70 -> SCI FORGEOT PROPERTY | L71: Impact vacance future | M71: =L71&"-"&C71 -> Impact vacance future-SCI FORGEOT PROPERTY | O71: =SUMIFS(O$260:O$10216,$L$260:$L$10216,$L71,$C$260:$C$10216,$C71) -> 0 | P71: =SUMIFS(P$260:P$10216,$L$260:$L$10216,$L71,$C$260:$C$10216,$C71) -> 0 | Q71: =SUMIFS(Q$260:Q$10216,$L$260:$L$10216,$L71,$C$260:$C$10216,$C71) -> 0 | R71: =SUMIFS(R$260:R$10216,$L$260:$L$10216,$L71,$C$260:$C$10216,$C71) -> 0 | S71: =SUMIFS(S$260:S$10216,$L$260:$L$10216,$L71,$C$260:$C$10216,$C71) -> 0 | T71: =SUMIFS(T$260:T$10216,$L$260:$L$10216,$L71,$C$260:$C$10216,$C71) -> 0 | U71: =SUMIFS(U$260:U$10216,$L$260:$L$10216,$L71,$C$260:$C$10216,$C71) -> 0 | V71: =SUMIFS(V$260:V$10216,$L$260:$L$10216,$L71,$C$260:$C$10216,$C71) -> 0 | ... BD71: =SUMIFS(BD$260:BD$10216,$L$260:$L$10216,$L71,$C$260:$C$10216,$C71) -> 0
C72: =C71 -> SCI FORGEOT PROPERTY | L72: Impact franchise future | M72: =L72&"-"&C72 -> Impact franchise future-SCI FORGEOT PROPERTY | O72: =SUMIFS(O$260:O$10216,$L$260:$L$10216,$L72,$C$260:$C$10216,$C72) -> 0 | P72: =SUMIFS(P$260:P$10216,$L$260:$L$10216,$L72,$C$260:$C$10216,$C72) -> 0 | Q72: =SUMIFS(Q$260:Q$10216,$L$260:$L$10216,$L72,$C$260:$C$10216,$C72) -> 0 | R72: =SUMIFS(R$260:R$10216,$L$260:$L$10216,$L72,$C$260:$C$10216,$C72) -> 0 | S72: =SUMIFS(S$260:S$10216,$L$260:$L$10216,$L72,$C$260:$C$10216,$C72) -> 0 | T72: =SUMIFS(T$260:T$10216,$L$260:$L$10216,$L72,$C$260:$C$10216,$C72) -> 0 | U72: =SUMIFS(U$260:U$10216,$L$260:$L$10216,$L72,$C$260:$C$10216,$C72) -> 0 | V72: =SUMIFS(V$260:V$10216,$L$260:$L$10216,$L72,$C$260:$C$10216,$C72) -> 0 | ... BD72: =SUMIFS(BD$260:BD$10216,$L$260:$L$10216,$L72,$C$260:$C$10216,$C72) -> 0
C73: =C72 -> SCI FORGEOT PROPERTY
C74: =C73 -> SCI FORGEOT PROPERTY | L74: Loyer | M74: =L74&"-"&C74 -> Loyer-SCI FORGEOT PROPERTY | O74: =SUMIFS(O$260:O$10216,$L$260:$L$10216,$L74,$C$260:$C$10216,$C74) -> 64666.315 | P74: =SUMIFS(P$260:P$10216,$L$260:$L$10216,$L74,$C$260:$C$10216,$C74) -> 7686.3844 | Q74: =SUMIFS(Q$260:Q$10216,$L$260:$L$10216,$L74,$C$260:$C$10216,$C74) -> 7686.3844 | R74: =SUMIFS(R$260:R$10216,$L$260:$L$10216,$L74,$C$260:$C$10216,$C74) -> 7727.5932 | S74: =SUMIFS(S$260:S$10216,$L$260:$L$10216,$L74,$C$260:$C$10216,$C74) -> 9024.5125 | T74: =SUMIFS(T$260:T$10216,$L$260:$L$10216,$L74,$C$260:$C$10216,$C74) -> 9057.3961 | U74: =SUMIFS(U$260:U$10216,$L$260:$L$10216,$L74,$C$260:$C$10216,$C74) -> 9057.3961 | V74: =SUMIFS(V$260:V$10216,$L$260:$L$10216,$L74,$C$260:$C$10216,$C74) -> 9161.7296 | ... BD74: =SUMIFS(BD$260:BD$10216,$L$260:$L$10216,$L74,$C$260:$C$10216,$C74) -> 14703.938
C75: =C74 -> SCI FORGEOT PROPERTY
C76: =C75 -> SCI FORGEOT PROPERTY | L76: DE / DAB | M76: =L76&"-"&C76 -> DE / DAB-SCI FORGEOT PROPERTY | O76: =SUMIFS(O$260:O$10216,$L$260:$L$10216,$L76,$C$260:$C$10216,$C76) -> 0 | P76: =SUMIFS(P$260:P$10216,$L$260:$L$10216,$L76,$C$260:$C$10216,$C76) -> 0 | Q76: =SUMIFS(Q$260:Q$10216,$L$260:$L$10216,$L76,$C$260:$C$10216,$C76) -> 0 | R76: =SUMIFS(R$260:R$10216,$L$260:$L$10216,$L76,$C$260:$C$10216,$C76) -> 0 | S76: =SUMIFS(S$260:S$10216,$L$260:$L$10216,$L76,$C$260:$C$10216,$C76) -> 0 | T76: =SUMIFS(T$260:T$10216,$L$260:$L$10216,$L76,$C$260:$C$10216,$C76) -> 0 | U76: =SUMIFS(U$260:U$10216,$L$260:$L$10216,$L76,$C$260:$C$10216,$C76) -> 0 | V76: =SUMIFS(V$260:V$10216,$L$260:$L$10216,$L76,$C$260:$C$10216,$C76) -> 0 | ... BD76: =SUMIFS(BD$260:BD$10216,$L$260:$L$10216,$L76,$C$260:$C$10216,$C76) -> 0
C77: =C76 -> SCI FORGEOT PROPERTY | L77: IR | M77: =L77&"-"&C77 -> IR-SCI FORGEOT PROPERTY | O77: =SUMIFS(O$260:O$10216,$L$260:$L$10216,$L77,$C$260:$C$10216,$C77) -> 0 | P77: =SUMIFS(P$260:P$10216,$L$260:$L$10216,$L77,$C$260:$C$10216,$C77) -> 0 | Q77: =SUMIFS(Q$260:Q$10216,$L$260:$L$10216,$L77,$C$260:$C$10216,$C77) -> 0 | R77: =SUMIFS(R$260:R$10216,$L$260:$L$10216,$L77,$C$260:$C$10216,$C77) -> 0 | S77: =SUMIFS(S$260:S$10216,$L$260:$L$10216,$L77,$C$260:$C$10216,$C77) -> 0 | T77: =SUMIFS(T$260:T$10216,$L$260:$L$10216,$L77,$C$260:$C$10216,$C77) -> 0 | U77: =SUMIFS(U$260:U$10216,$L$260:$L$10216,$L77,$C$260:$C$10216,$C77) -> 0 | V77: =SUMIFS(V$260:V$10216,$L$260:$L$10216,$L77,$C$260:$C$10216,$C77) -> 0 | ... BD77: =SUMIFS(BD$260:BD$10216,$L$260:$L$10216,$L77,$C$260:$C$10216,$C77) -> 0
C78: =C77 -> SCI FORGEOT PROPERTY | L78: FOC | M78: =L78&"-"&C78 -> FOC-SCI FORGEOT PROPERTY | O78: =SUMIFS(O$260:O$10216,$L$260:$L$10216,$L78,$C$260:$C$10216,$C78) -> 0 | P78: =SUMIFS(P$260:P$10216,$L$260:$L$10216,$L78,$C$260:$C$10216,$C78) -> 0 | Q78: =SUMIFS(Q$260:Q$10216,$L$260:$L$10216,$L78,$C$260:$C$10216,$C78) -> 0 | R78: =SUMIFS(R$260:R$10216,$L$260:$L$10216,$L78,$C$260:$C$10216,$C78) -> 0 | S78: =SUMIFS(S$260:S$10216,$L$260:$L$10216,$L78,$C$260:$C$10216,$C78) -> 0 | T78: =SUMIFS(T$260:T$10216,$L$260:$L$10216,$L78,$C$260:$C$10216,$C78) -> 0 | U78: =SUMIFS(U$260:U$10216,$L$260:$L$10216,$L78,$C$260:$C$10216,$C78) -> 0 | V78: =SUMIFS(V$260:V$10216,$L$260:$L$10216,$L78,$C$260:$C$10216,$C78) -> 0 | ... BD78: =SUMIFS(BD$260:BD$10216,$L$260:$L$10216,$L78,$C$260:$C$10216,$C78) -> 0
C79: =C78 -> SCI FORGEOT PROPERTY | L79: Travaux bailleur | M79: =L79&"-"&C79 -> Travaux bailleur-SCI FORGEOT PROPERTY | O79: =SUMIFS(O$260:O$10216,$L$260:$L$10216,$L79,$C$260:$C$10216,$C79) -> 0 | P79: =SUMIFS(P$260:P$10216,$L$260:$L$10216,$L79,$C$260:$C$10216,$C79) -> 0 | Q79: =SUMIFS(Q$260:Q$10216,$L$260:$L$10216,$L79,$C$260:$C$10216,$C79) -> 0 | R79: =SUMIFS(R$260:R$10216,$L$260:$L$10216,$L79,$C$260:$C$10216,$C79) -> 0 | S79: =SUMIFS(S$260:S$10216,$L$260:$L$10216,$L79,$C$260:$C$10216,$C79) -> 0 | T79: =SUMIFS(T$260:T$10216,$L$260:$L$10216,$L79,$C$260:$C$10216,$C79) -> 0 | U79: =SUMIFS(U$260:U$10216,$L$260:$L$10216,$L79,$C$260:$C$10216,$C79) -> 0 | V79: =SUMIFS(V$260:V$10216,$L$260:$L$10216,$L79,$C$260:$C$10216,$C79) -> 0 | ... BD79: =SUMIFS(BD$260:BD$10216,$L$260:$L$10216,$L79,$C$260:$C$10216,$C79) -> 0
C80: =C79 -> SCI FORGEOT PROPERTY | L80: Charges si vacant | M80: =L80&"-"&C80 -> Charges si vacant-SCI FORGEOT PROPERTY | O80: =SUMIFS(O$260:O$10216,$L$260:$L$10216,$L80,$C$260:$C$10216,$C80) -> 0 | P80: =SUMIFS(P$260:P$10216,$L$260:$L$10216,$L80,$C$260:$C$10216,$C80) -> 0 | Q80: =SUMIFS(Q$260:Q$10216,$L$260:$L$10216,$L80,$C$260:$C$10216,$C80) -> 0 | R80: =SUMIFS(R$260:R$10216,$L$260:$L$10216,$L80,$C$260:$C$10216,$C80) -> 0 | S80: =SUMIFS(S$260:S$10216,$L$260:$L$10216,$L80,$C$260:$C$10216,$C80) -> 0 | T80: =SUMIFS(T$260:T$10216,$L$260:$L$10216,$L80,$C$260:$C$10216,$C80) -> 0 | U80: =SUMIFS(U$260:U$10216,$L$260:$L$10216,$L80,$C$260:$C$10216,$C80) -> 0 | V80: =SUMIFS(V$260:V$10216,$L$260:$L$10216,$L80,$C$260:$C$10216,$C80) -> 0 | ... BD80: =SUMIFS(BD$260:BD$10216,$L$260:$L$10216,$L80,$C$260:$C$10216,$C80) -> 0
C81: =C80 -> SCI FORGEOT PROPERTY
C83: SCI RETAIL RENNES 1 | D83: =C83 -> SCI RETAIL RENNES 1
C84: =C83 -> SCI RETAIL RENNES 1
C85: =C84 -> SCI RETAIL RENNES 1 | L85: % Palier | O85: =SUMIFS(O$260:O$10216,$L$260:$L$10216,$L85,$C$260:$C$10216,$C85)/COUNTIFS($L$260:$L$10216,$L85,$C$260:$C$10216,$C85) -> 0.12 | P85: =SUMIFS(P$260:P$10216,$L$260:$L$10216,$L85,$C$260:$C$10216,$C85)/COUNTIFS($L$260:$L$10216,$L85,$C$260:$C$10216,$C85) -> 0.12 | Q85: =SUMIFS(Q$260:Q$10216,$L$260:$L$10216,$L85,$C$260:$C$10216,$C85)/COUNTIFS($L$260:$L$10216,$L85,$C$260:$C$10216,$C85) -> 0.08 | R85: =SUMIFS(R$260:R$10216,$L$260:$L$10216,$L85,$C$260:$C$10216,$C85)/COUNTIFS($L$260:$L$10216,$L85,$C$260:$C$10216,$C85) -> 0.027252747 | S85: =SUMIFS(S$260:S$10216,$L$260:$L$10216,$L85,$C$260:$C$10216,$C85)/COUNTIFS($L$260:$L$10216,$L85,$C$260:$C$10216,$C85) -> 0 | T85: =SUMIFS(T$260:T$10216,$L$260:$L$10216,$L85,$C$260:$C$10216,$C85)/COUNTIFS($L$260:$L$10216,$L85,$C$260:$C$10216,$C85) -> 0 | U85: =SUMIFS(U$260:U$10216,$L$260:$L$10216,$L85,$C$260:$C$10216,$C85)/COUNTIFS($L$260:$L$10216,$L85,$C$260:$C$10216,$C85) -> 0 | V85: =SUMIFS(V$260:V$10216,$L$260:$L$10216,$L85,$C$260:$C$10216,$C85)/COUNTIFS($L$260:$L$10216,$L85,$C$260:$C$10216,$C85) -> 0 | ... BD85: =SUMIFS(BD$260:BD$10216,$L$260:$L$10216,$L85,$C$260:$C$10216,$C85)/COUNTIFS($L$260:$L$10216,$L85,$C$260:$C$10216,$C85) -> 0
C86: =C85 -> SCI RETAIL RENNES 1 | L86: % Loyer | O86: =SUMIFS(O$260:O$10216,$L$260:$L$10216,$L86,$C$260:$C$10216,$C86)/COUNTIFS($L$260:$L$10216,$L86,$C$260:$C$10216,$C86) -> 0.90434783 | P86: =SUMIFS(P$260:P$10216,$L$260:$L$10216,$L86,$C$260:$C$10216,$C86)/COUNTIFS($L$260:$L$10216,$L86,$C$260:$C$10216,$C86) -> 0.88 | Q86: =SUMIFS(Q$260:Q$10216,$L$260:$L$10216,$L86,$C$260:$C$10216,$C86)/COUNTIFS($L$260:$L$10216,$L86,$C$260:$C$10216,$C86) -> 0.88 | R86: =SUMIFS(R$260:R$10216,$L$260:$L$10216,$L86,$C$260:$C$10216,$C86)/COUNTIFS($L$260:$L$10216,$L86,$C$260:$C$10216,$C86) -> 0.88 | S86: =SUMIFS(S$260:S$10216,$L$260:$L$10216,$L86,$C$260:$C$10216,$C86)/COUNTIFS($L$260:$L$10216,$L86,$C$260:$C$10216,$C86) -> 0.84 | T86: =SUMIFS(T$260:T$10216,$L$260:$L$10216,$L86,$C$260:$C$10216,$C86)/COUNTIFS($L$260:$L$10216,$L86,$C$260:$C$10216,$C86) -> 0.84 | U86: =SUMIFS(U$260:U$10216,$L$260:$L$10216,$L86,$C$260:$C$10216,$C86)/COUNTIFS($L$260:$L$10216,$L86,$C$260:$C$10216,$C86) -> 0.79648352 | V86: =SUMIFS(V$260:V$10216,$L$260:$L$10216,$L86,$C$260:$C$10216,$C86)/COUNTIFS($L$260:$L$10216,$L86,$C$260:$C$10216,$C86) -> 0.76 | ... BD86: =SUMIFS(BD$260:BD$10216,$L$260:$L$10216,$L86,$C$260:$C$10216,$C86)/COUNTIFS($L$260:$L$10216,$L86,$C$260:$C$10216,$C86) -> 0
C87: =C86 -> SCI RETAIL RENNES 1 | L87: % Vacance loyer futur | O87: =SUMIFS(O$260:O$10216,$L$260:$L$10216,$L87,$C$260:$C$10216,$C87)/COUNTIFS($L$260:$L$10216,$L87,$C$260:$C$10216,$C87) -> 0.00043478261 | P87: =SUMIFS(P$260:P$10216,$L$260:$L$10216,$L87,$C$260:$C$10216,$C87)/COUNTIFS($L$260:$L$10216,$L87,$C$260:$C$10216,$C87) -> 0 | Q87: =SUMIFS(Q$260:Q$10216,$L$260:$L$10216,$L87,$C$260:$C$10216,$C87)/COUNTIFS($L$260:$L$10216,$L87,$C$260:$C$10216,$C87) -> 0 | R87: =SUMIFS(R$260:R$10216,$L$260:$L$10216,$L87,$C$260:$C$10216,$C87)/COUNTIFS($L$260:$L$10216,$L87,$C$260:$C$10216,$C87) -> 0 | S87: =SUMIFS(S$260:S$10216,$L$260:$L$10216,$L87,$C$260:$C$10216,$C87)/COUNTIFS($L$260:$L$10216,$L87,$C$260:$C$10216,$C87) -> 0 | T87: =SUMIFS(T$260:T$10216,$L$260:$L$10216,$L87,$C$260:$C$10216,$C87)/COUNTIFS($L$260:$L$10216,$L87,$C$260:$C$10216,$C87) -> 0 | U87: =SUMIFS(U$260:U$10216,$L$260:$L$10216,$L87,$C$260:$C$10216,$C87)/COUNTIFS($L$260:$L$10216,$L87,$C$260:$C$10216,$C87) -> 0 | V87: =SUMIFS(V$260:V$10216,$L$260:$L$10216,$L87,$C$260:$C$10216,$C87)/COUNTIFS($L$260:$L$10216,$L87,$C$260:$C$10216,$C87) -> 0 | ... BD87: =SUMIFS(BD$260:BD$10216,$L$260:$L$10216,$L87,$C$260:$C$10216,$C87)/COUNTIFS($L$260:$L$10216,$L87,$C$260:$C$10216,$C87) -> 0
C88: =C87 -> SCI RETAIL RENNES 1 | L88: % Franchise loyer futur | O88: =SUMIFS(O$260:O$10216,$L$260:$L$10216,$L88,$C$260:$C$10216,$C88)/COUNTIFS($L$260:$L$10216,$L88,$C$260:$C$10216,$C88) -> 0.026521739 | P88: =SUMIFS(P$260:P$10216,$L$260:$L$10216,$L88,$C$260:$C$10216,$C88)/COUNTIFS($L$260:$L$10216,$L88,$C$260:$C$10216,$C88) -> 0 | Q88: =SUMIFS(Q$260:Q$10216,$L$260:$L$10216,$L88,$C$260:$C$10216,$C88)/COUNTIFS($L$260:$L$10216,$L88,$C$260:$C$10216,$C88) -> 0 | R88: =SUMIFS(R$260:R$10216,$L$260:$L$10216,$L88,$C$260:$C$10216,$C88)/COUNTIFS($L$260:$L$10216,$L88,$C$260:$C$10216,$C88) -> 0 | S88: =SUMIFS(S$260:S$10216,$L$260:$L$10216,$L88,$C$260:$C$10216,$C88)/COUNTIFS($L$260:$L$10216,$L88,$C$260:$C$10216,$C88) -> 0 | T88: =SUMIFS(T$260:T$10216,$L$260:$L$10216,$L88,$C$260:$C$10216,$C88)/COUNTIFS($L$260:$L$10216,$L88,$C$260:$C$10216,$C88) -> 0 | U88: =SUMIFS(U$260:U$10216,$L$260:$L$10216,$L88,$C$260:$C$10216,$C88)/COUNTIFS($L$260:$L$10216,$L88,$C$260:$C$10216,$C88) -> 0 | V88: =SUMIFS(V$260:V$10216,$L$260:$L$10216,$L88,$C$260:$C$10216,$C88)/COUNTIFS($L$260:$L$10216,$L88,$C$260:$C$10216,$C88) -> 0 | ... BD88: =SUMIFS(BD$260:BD$10216,$L$260:$L$10216,$L88,$C$260:$C$10216,$C88)/COUNTIFS($L$260:$L$10216,$L88,$C$260:$C$10216,$C88) -> 0
C89: =C88 -> SCI RETAIL RENNES 1 | L89: % Loyer futur | O89: =SUMIFS(O$260:O$10216,$L$260:$L$10216,$L89,$C$260:$C$10216,$C89)/COUNTIFS($L$260:$L$10216,$L89,$C$260:$C$10216,$C89) -> 0.096086957 | P89: =SUMIFS(P$260:P$10216,$L$260:$L$10216,$L89,$C$260:$C$10216,$C89)/COUNTIFS($L$260:$L$10216,$L89,$C$260:$C$10216,$C89) -> 0.12 | Q89: =SUMIFS(Q$260:Q$10216,$L$260:$L$10216,$L89,$C$260:$C$10216,$C89)/COUNTIFS($L$260:$L$10216,$L89,$C$260:$C$10216,$C89) -> 0.12 | R89: =SUMIFS(R$260:R$10216,$L$260:$L$10216,$L89,$C$260:$C$10216,$C89)/COUNTIFS($L$260:$L$10216,$L89,$C$260:$C$10216,$C89) -> 0.12043956 | S89: =SUMIFS(S$260:S$10216,$L$260:$L$10216,$L89,$C$260:$C$10216,$C89)/COUNTIFS($L$260:$L$10216,$L89,$C$260:$C$10216,$C89) -> 0.16 | T89: =SUMIFS(T$260:T$10216,$L$260:$L$10216,$L89,$C$260:$C$10216,$C89)/COUNTIFS($L$260:$L$10216,$L89,$C$260:$C$10216,$C89) -> 0.16043478 | U89: =SUMIFS(U$260:U$10216,$L$260:$L$10216,$L89,$C$260:$C$10216,$C89)/COUNTIFS($L$260:$L$10216,$L89,$C$260:$C$10216,$C89) -> 0.20395604 | V89: =SUMIFS(V$260:V$10216,$L$260:$L$10216,$L89,$C$260:$C$10216,$C89)/COUNTIFS($L$260:$L$10216,$L89,$C$260:$C$10216,$C89) -> 0.24 | ... BD89: =SUMIFS(BD$260:BD$10216,$L$260:$L$10216,$L89,$C$260:$C$10216,$C89)/COUNTIFS($L$260:$L$10216,$L89,$C$260:$C$10216,$C89) -> 1
C90: =C89 -> SCI RETAIL RENNES 1
C91: =C90 -> SCI RETAIL RENNES 1 | L91: Indice loyer | M91: 1 | N91: 1 | O91: =SUMIFS(O$260:O$10216,$L$260:$L$10216,$L91,$C$260:$C$10216,$C91)/COUNTIFS($L$260:$L$10216,$L91,$C$260:$C$10216,$C91) -> 1.007487 | P91: =SUMIFS(P$260:P$10216,$L$260:$L$10216,$L91,$C$260:$C$10216,$C91)/COUNTIFS($L$260:$L$10216,$L91,$C$260:$C$10216,$C91) -> 1.0102174 | Q91: =SUMIFS(Q$260:Q$10216,$L$260:$L$10216,$L91,$C$260:$C$10216,$C91)/COUNTIFS($L$260:$L$10216,$L91,$C$260:$C$10216,$C91) -> 1.0145111 | R91: =SUMIFS(R$260:R$10216,$L$260:$L$10216,$L91,$C$260:$C$10216,$C91)/COUNTIFS($L$260:$L$10216,$L91,$C$260:$C$10216,$C91) -> 1.0160618 | S91: =SUMIFS(S$260:S$10216,$L$260:$L$10216,$L91,$C$260:$C$10216,$C91)/COUNTIFS($L$260:$L$10216,$L91,$C$260:$C$10216,$C91) -> 1.0194183 | T91: =SUMIFS(T$260:T$10216,$L$260:$L$10216,$L91,$C$260:$C$10216,$C91)/COUNTIFS($L$260:$L$10216,$L91,$C$260:$C$10216,$C91) -> 1.0208109 | U91: =SUMIFS(U$260:U$10216,$L$260:$L$10216,$L91,$C$260:$C$10216,$C91)/COUNTIFS($L$260:$L$10216,$L91,$C$260:$C$10216,$C91) -> 1.0246594 | V91: =SUMIFS(V$260:V$10216,$L$260:$L$10216,$L91,$C$260:$C$10216,$C91)/COUNTIFS($L$260:$L$10216,$L91,$C$260:$C$10216,$C91) -> 1.0262224 | ... BD91: =SUMIFS(BD$260:BD$10216,$L$260:$L$10216,$L91,$C$260:$C$10216,$C91)/COUNTIFS($L$260:$L$10216,$L91,$C$260:$C$10216,$C91) -> 1.1164458
C92: =C91 -> SCI RETAIL RENNES 1
C93: =C92 -> SCI RETAIL RENNES 1 | L93: Loyer bail | M93: =L93&"-"&C93 -> Loyer bail-SCI RETAIL RENNES 1 | O93: =SUMIFS(O$260:O$10216,$L$260:$L$10216,$L93,$C$260:$C$10216,$C93) -> 447128.59 | P93: =SUMIFS(P$260:P$10216,$L$260:$L$10216,$L93,$C$260:$C$10216,$C93) -> 453409.24 | Q93: =SUMIFS(Q$260:Q$10216,$L$260:$L$10216,$L93,$C$260:$C$10216,$C93) -> 453409.24 | R93: =SUMIFS(R$260:R$10216,$L$260:$L$10216,$L93,$C$260:$C$10216,$C93) -> 453573.69 | S93: =SUMIFS(S$260:S$10216,$L$260:$L$10216,$L93,$C$260:$C$10216,$C93) -> 456373.87 | T93: =SUMIFS(T$260:T$10216,$L$260:$L$10216,$L93,$C$260:$C$10216,$C93) -> 456408.84 | U93: =SUMIFS(U$260:U$10216,$L$260:$L$10216,$L93,$C$260:$C$10216,$C93) -> 457047.26 | V93: =SUMIFS(V$260:V$10216,$L$260:$L$10216,$L93,$C$260:$C$10216,$C93) -> 459805.65 | ... BD93: =SUMIFS(BD$260:BD$10216,$L$260:$L$10216,$L93,$C$260:$C$10216,$C93) -> 513671.57
C94: =C93 -> SCI RETAIL RENNES 1 | L94: Loyer indexé | M94: =L94&"-"&C94 -> Loyer indexé-SCI RETAIL RENNES 1 | O94: =SUMIFS(O$260:O$10216,$L$260:$L$10216,$L94,$C$260:$C$10216,$C94) -> 467781.28 | P94: =SUMIFS(P$260:P$10216,$L$260:$L$10216,$L94,$C$260:$C$10216,$C94) -> 474329.58 | Q94: =SUMIFS(Q$260:Q$10216,$L$260:$L$10216,$L94,$C$260:$C$10216,$C94) -> 476638.36 | R94: =SUMIFS(R$260:R$10216,$L$260:$L$10216,$L94,$C$260:$C$10216,$C94) -> 477494.68 | S94: =SUMIFS(S$260:S$10216,$L$260:$L$10216,$L94,$C$260:$C$10216,$C94) -> 480026.79 | T94: =SUMIFS(T$260:T$10216,$L$260:$L$10216,$L94,$C$260:$C$10216,$C94) -> 480640.19 | U94: =SUMIFS(U$260:U$10216,$L$260:$L$10216,$L94,$C$260:$C$10216,$C94) -> 483142.35 | V94: =SUMIFS(V$260:V$10216,$L$260:$L$10216,$L94,$C$260:$C$10216,$C94) -> 485351.8 | ... BD94: =SUMIFS(BD$260:BD$10216,$L$260:$L$10216,$L94,$C$260:$C$10216,$C94) -> 544680.64
C95: =C94 -> SCI RETAIL RENNES 1 | L95: Impact palier | M95: =L95&"-"&C95 -> Impact palier-SCI RETAIL RENNES 1 | O95: =SUMIFS(O$260:O$10216,$L$260:$L$10216,$L95,$C$260:$C$10216,$C95) -> -8766.2711 | P95: =SUMIFS(P$260:P$10216,$L$260:$L$10216,$L95,$C$260:$C$10216,$C95) -> -10451.054 | Q95: =SUMIFS(Q$260:Q$10216,$L$260:$L$10216,$L95,$C$260:$C$10216,$C95) -> -10451.054 | R95: =SUMIFS(R$260:R$10216,$L$260:$L$10216,$L95,$C$260:$C$10216,$C95) -> -6139.9687 | S95: =SUMIFS(S$260:S$10216,$L$260:$L$10216,$L95,$C$260:$C$10216,$C95) -> -3342.3913 | T95: =SUMIFS(T$260:T$10216,$L$260:$L$10216,$L95,$C$260:$C$10216,$C95) -> -2500 | U95: =SUMIFS(U$260:U$10216,$L$260:$L$10216,$L95,$C$260:$C$10216,$C95) -> -2500 | V95: =SUMIFS(V$260:V$10216,$L$260:$L$10216,$L95,$C$260:$C$10216,$C95) -> -2500 | ... BD95: =SUMIFS(BD$260:BD$10216,$L$260:$L$10216,$L95,$C$260:$C$10216,$C95) -> 0
C96: =C95 -> SCI RETAIL RENNES 1 | L96: Impact vacance future | M96: =L96&"-"&C96 -> Impact vacance future-SCI RETAIL RENNES 1 | O96: =SUMIFS(O$260:O$10216,$L$260:$L$10216,$L96,$C$260:$C$10216,$C96) -> 0 | P96: =SUMIFS(P$260:P$10216,$L$260:$L$10216,$L96,$C$260:$C$10216,$C96) -> 0 | Q96: =SUMIFS(Q$260:Q$10216,$L$260:$L$10216,$L96,$C$260:$C$10216,$C96) -> 0 | R96: =SUMIFS(R$260:R$10216,$L$260:$L$10216,$L96,$C$260:$C$10216,$C96) -> 0 | S96: =SUMIFS(S$260:S$10216,$L$260:$L$10216,$L96,$C$260:$C$10216,$C96) -> 0 | T96: =SUMIFS(T$260:T$10216,$L$260:$L$10216,$L96,$C$260:$C$10216,$C96) -> 0 | U96: =SUMIFS(U$260:U$10216,$L$260:$L$10216,$L96,$C$260:$C$10216,$C96) -> 0 | V96: =SUMIFS(V$260:V$10216,$L$260:$L$10216,$L96,$C$260:$C$10216,$C96) -> 0 | ... BD96: =SUMIFS(BD$260:BD$10216,$L$260:$L$10216,$L96,$C$260:$C$10216,$C96) -> 0
C97: =C96 -> SCI RETAIL RENNES 1 | L97: Impact franchise future | M97: =L97&"-"&C97 -> Impact franchise future-SCI RETAIL RENNES 1 | O97: =SUMIFS(O$260:O$10216,$L$260:$L$10216,$L97,$C$260:$C$10216,$C97) -> 0 | P97: =SUMIFS(P$260:P$10216,$L$260:$L$10216,$L97,$C$260:$C$10216,$C97) -> 0 | Q97: =SUMIFS(Q$260:Q$10216,$L$260:$L$10216,$L97,$C$260:$C$10216,$C97) -> 0 | R97: =SUMIFS(R$260:R$10216,$L$260:$L$10216,$L97,$C$260:$C$10216,$C97) -> 0 | S97: =SUMIFS(S$260:S$10216,$L$260:$L$10216,$L97,$C$260:$C$10216,$C97) -> 0 | T97: =SUMIFS(T$260:T$10216,$L$260:$L$10216,$L97,$C$260:$C$10216,$C97) -> 0 | U97: =SUMIFS(U$260:U$10216,$L$260:$L$10216,$L97,$C$260:$C$10216,$C97) -> 0 | V97: =SUMIFS(V$260:V$10216,$L$260:$L$10216,$L97,$C$260:$C$10216,$C97) -> 0 | ... BD97: =SUMIFS(BD$260:BD$10216,$L$260:$L$10216,$L97,$C$260:$C$10216,$C97) -> 0
C98: =C97 -> SCI RETAIL RENNES 1
C99: =C98 -> SCI RETAIL RENNES 1 | L99: Loyer | M99: =L99&"-"&C99 -> Loyer-SCI RETAIL RENNES 1 | O99: =SUMIFS(O$260:O$10216,$L$260:$L$10216,$L99,$C$260:$C$10216,$C99) -> 441678.97 | P99: =SUMIFS(P$260:P$10216,$L$260:$L$10216,$L99,$C$260:$C$10216,$C99) -> 463878.53 | Q99: =SUMIFS(Q$260:Q$10216,$L$260:$L$10216,$L99,$C$260:$C$10216,$C99) -> 466187.31 | R99: =SUMIFS(R$260:R$10216,$L$260:$L$10216,$L99,$C$260:$C$10216,$C99) -> 471354.71 | S99: =SUMIFS(S$260:S$10216,$L$260:$L$10216,$L99,$C$260:$C$10216,$C99) -> 476684.4 | T99: =SUMIFS(T$260:T$10216,$L$260:$L$10216,$L99,$C$260:$C$10216,$C99) -> 478140.19 | U99: =SUMIFS(U$260:U$10216,$L$260:$L$10216,$L99,$C$260:$C$10216,$C99) -> 480642.35 | V99: =SUMIFS(V$260:V$10216,$L$260:$L$10216,$L99,$C$260:$C$10216,$C99) -> 482851.8 | ... BD99: =SUMIFS(BD$260:BD$10216,$L$260:$L$10216,$L99,$C$260:$C$10216,$C99) -> 544680.64
C100: =C99 -> SCI RETAIL RENNES 1
C101: =C100 -> SCI RETAIL RENNES 1 | L101: DE / DAB | M101: =L101&"-"&C101 -> DE / DAB-SCI RETAIL RENNES 1 | O101: =SUMIFS(O$260:O$10216,$L$260:$L$10216,$L101,$C$260:$C$10216,$C101) -> 0 | P101: =SUMIFS(P$260:P$10216,$L$260:$L$10216,$L101,$C$260:$C$10216,$C101) -> 0 | Q101: =SUMIFS(Q$260:Q$10216,$L$260:$L$10216,$L101,$C$260:$C$10216,$C101) -> 0 | R101: =SUMIFS(R$260:R$10216,$L$260:$L$10216,$L101,$C$260:$C$10216,$C101) -> 0 | S101: =SUMIFS(S$260:S$10216,$L$260:$L$10216,$L101,$C$260:$C$10216,$C101) -> 0 | T101: =SUMIFS(T$260:T$10216,$L$260:$L$10216,$L101,$C$260:$C$10216,$C101) -> 0 | U101: =SUMIFS(U$260:U$10216,$L$260:$L$10216,$L101,$C$260:$C$10216,$C101) -> 0 | V101: =SUMIFS(V$260:V$10216,$L$260:$L$10216,$L101,$C$260:$C$10216,$C101) -> 0 | ... BD101: =SUMIFS(BD$260:BD$10216,$L$260:$L$10216,$L101,$C$260:$C$10216,$C101) -> 0
C102: =C101 -> SCI RETAIL RENNES 1 | L102: IR | M102: =L102&"-"&C102 -> IR-SCI RETAIL RENNES 1 | O102: =SUMIFS(O$260:O$10216,$L$260:$L$10216,$L102,$C$260:$C$10216,$C102) -> 400000 | P102: =SUMIFS(P$260:P$10216,$L$260:$L$10216,$L102,$C$260:$C$10216,$C102) -> 0 | Q102: =SUMIFS(Q$260:Q$10216,$L$260:$L$10216,$L102,$C$260:$C$10216,$C102) -> 0 | R102: =SUMIFS(R$260:R$10216,$L$260:$L$10216,$L102,$C$260:$C$10216,$C102) -> 0 | S102: =SUMIFS(S$260:S$10216,$L$260:$L$10216,$L102,$C$260:$C$10216,$C102) -> 0 | T102: =SUMIFS(T$260:T$10216,$L$260:$L$10216,$L102,$C$260:$C$10216,$C102) -> 0 | U102: =SUMIFS(U$260:U$10216,$L$260:$L$10216,$L102,$C$260:$C$10216,$C102) -> 0 | V102: =SUMIFS(V$260:V$10216,$L$260:$L$10216,$L102,$C$260:$C$10216,$C102) -> 0 | ... BD102: =SUMIFS(BD$260:BD$10216,$L$260:$L$10216,$L102,$C$260:$C$10216,$C102) -> 0
C103: =C102 -> SCI RETAIL RENNES 1 | L103: FOC | M103: =L103&"-"&C103 -> FOC-SCI RETAIL RENNES 1 | O103: =SUMIFS(O$260:O$10216,$L$260:$L$10216,$L103,$C$260:$C$10216,$C103) -> 0 | P103: =SUMIFS(P$260:P$10216,$L$260:$L$10216,$L103,$C$260:$C$10216,$C103) -> 0 | Q103: =SUMIFS(Q$260:Q$10216,$L$260:$L$10216,$L103,$C$260:$C$10216,$C103) -> 0 | R103: =SUMIFS(R$260:R$10216,$L$260:$L$10216,$L103,$C$260:$C$10216,$C103) -> 0 | S103: =SUMIFS(S$260:S$10216,$L$260:$L$10216,$L103,$C$260:$C$10216,$C103) -> 0 | T103: =SUMIFS(T$260:T$10216,$L$260:$L$10216,$L103,$C$260:$C$10216,$C103) -> 0 | U103: =SUMIFS(U$260:U$10216,$L$260:$L$10216,$L103,$C$260:$C$10216,$C103) -> 0 | V103: =SUMIFS(V$260:V$10216,$L$260:$L$10216,$L103,$C$260:$C$10216,$C103) -> 0 | ... BD103: =SUMIFS(BD$260:BD$10216,$L$260:$L$10216,$L103,$C$260:$C$10216,$C103) -> 0
C104: =C103 -> SCI RETAIL RENNES 1 | L104: Travaux bailleur | M104: =L104&"-"&C104 -> Travaux bailleur-SCI RETAIL RENNES 1 | O104: =SUMIFS(O$260:O$10216,$L$260:$L$10216,$L104,$C$260:$C$10216,$C104) -> 0 | P104: =SUMIFS(P$260:P$10216,$L$260:$L$10216,$L104,$C$260:$C$10216,$C104) -> 0 | Q104: =SUMIFS(Q$260:Q$10216,$L$260:$L$10216,$L104,$C$260:$C$10216,$C104) -> 0 | R104: =SUMIFS(R$260:R$10216,$L$260:$L$10216,$L104,$C$260:$C$10216,$C104) -> 0 | S104: =SUMIFS(S$260:S$10216,$L$260:$L$10216,$L104,$C$260:$C$10216,$C104) -> 0 | T104: =SUMIFS(T$260:T$10216,$L$260:$L$10216,$L104,$C$260:$C$10216,$C104) -> 0 | U104: =SUMIFS(U$260:U$10216,$L$260:$L$10216,$L104,$C$260:$C$10216,$C104) -> 0 | V104: =SUMIFS(V$260:V$10216,$L$260:$L$10216,$L104,$C$260:$C$10216,$C104) -> 0 | ... BD104: =SUMIFS(BD$260:BD$10216,$L$260:$L$10216,$L104,$C$260:$C$10216,$C104) -> 0
...

Sheet Indices
B2: Indices | C2: 2022 | D2: =C2+1 -> 2023 | E2: =D2+1 -> 2024 | F2: =E2+1 -> 2025 | G2: =F2+1 -> 2026 | H2: =G2+1 -> 2027 | I2: =H2+1 -> 2028 | J2: =I2+1 -> 2029 | K2: =J2+1 -> 2030 | ... S2: =R2+1 -> 2038
B3: ILC | C3: 0.02 | D3: 0.01 | E3: 0.01 | F3: 0.01 | G3: 0.01 | H3: 0.01 | I3: 0.01 | J3: 0.01 | K3: 0.01 | L3: 0.01 | M3: 0.01 | N3: 0.01 | O3: 0.01 | P3: 0.01 | Q3: 0.01 | R3: 0.01 | S3: 0.01
B4: ICC | C4: 0.02 | D4: 0.01 | E4: 0.01 | F4: 0.01 | G4: 0.01 | H4: 0.01 | I4: 0.01 | J4: 0.01 | K4: 0.01 | L4: 0.01 | M4: 0.01 | N4: 0.01 | O4: 0.01 | P4: 0.01 | Q4: 0.01 | R4: 0.01 | S4: 0.01
B5: IRL | C5: 0.01 | D5: 0.01 | E5: 0.01 | F5: 0.01 | G5: 0.01 | H5: 0.01 | I5: 0.01 | J5: 0.01 | K5: 0.01 | L5: 0.01 | M5: 0.01 | N5: 0.01 | O5: 0.01 | P5: 0.01 | Q5: 0.01 | R5: 0.01 | S5: 0.01
B6: IRL2008 | C6: 0.01 | D6: 0.01 | E6: 0.01 | F6: 0.01 | G6: 0.01 | H6: 0.01 | I6: 0.01 | J6: 0.01 | K6: 0.01 | L6: 0.01 | M6: 0.01 | N6: 0.01 | O6: 0.01 | P6: 0.01 | Q6: 0.01 | R6: 0.01 | S6: 0.01
B7: ILAT | C7: 0.01 | D7: 0.01 | E7: 0.01 | F7: 0.01 | G7: 0.01 | H7: 0.01 | I7: 0.01 | J7: 0.01 | K7: 0.01 | L7: 0.01 | M7: 0.01 | N7: 0.01 | O7: 0.01 | P7: 0.01 | Q7: 0.01 | R7: 0.01 | S7: 0.01

Sheet Liste
B3: Localisation | D3: Copropriété | F3: 1 | G3: 1 | I3: Oui | K3: Restauration | N3: A | P3: France
B4: Paris | D4: Monopropriété | F4: 2 | G4: 1 | I4: Non | K4: Centre-commercial | N4: B | P4: Etranger
B5: Région | D5: Division en volume | F5: 3 | G5: 1 | K5: Commerce spécialisé | N5: C
F6: 4 | G6: 2 | K6: Crèche / Ecole | N6: D
F7: 5 | G7: 2 | K7: Service de soin | N7: E
F8: 6 | G8: 2 | I8: Oui bon état | K8: Théâtre / Cinéma / Musée | N8: F
F9: 7 | G9: 3 | I9: Oui mauvais état | K9: Salle de sport | N9: G
F10: 8 | G10: 3 | I10: Non
F11: 9 | G11: 3
F12: 10 | G12: 4
F13: 11 | G13: 4
F14: 12 | G14: 4
B18: Personnes présentes | F18: Contexte | I18: Type de Candidat | K18: Conditions Suspensives | N18: Paiement du loyer | P18: Clause d'accession
B19: Arieu Thomas | F19: Offre non sollicitée | I19: Personne Physique | K19: Financement | N19: Prélèvement | P19: Immédiate
B20: Bellenguez Anne-Charlotte | F20: Local vacant | I20: SAS | K20: Autorisations administratives | N20: Virement | P20: Fin du bail
B21: Divies Robin | F21: Résil / recomm | I21: SARL | K21: Extraction | P21: Fin de jouissance
B22: El Baghli Imane | F22: Stratégie de renouvellement | I22: EURL | K22: Libération des locaux
B23: El Madhi L'Yazid | F23: Break option | I23: Société en formation | K23: Autre
B24: Forgeot Maxime | F24: Procédure
B25: Langlais Thibaut | F25: Interception cession
B26: Roy Yohan | F26: Autre
B27: Verneuil Lucas | F27: [à compléter]
B30: Procédures en cours
B31: Non
B32: Liquidation judiciaire
B33: Redressement judiciaire
B34: Procédure pour impayés
B35: COR
B36: RR
B37: Autres
B41: Valideurs | C41: 50000 | D41: Langlais Thibaut
B42: <= | C42: 100000 | D42: Bellenguez Anne-Charlotte
B43: =$B$42 -> <= | D43: Forgeot Maxime
